{
  "blocks": [
    {
      "id": "/page/0/SectionHeader/0",
      "block_type": "SectionHeader",
      "html": "<h2><i>Beslissing nr. 2002-C/C-33 van 25 april 2002</i></h2>",
      "page": 136,
      "polygon": [
        [
          71.58984375,
          85.27752685546875
        ],
        [
          321.86328125,
          85.27752685546875
        ],
        [
          321.86328125,
          97.27752685546875
        ],
        [
          71.58984375,
          97.27752685546875
        ]
      ],
      "bbox": [
        71.58984375,
        85.27752685546875,
        321.86328125,
        97.27752685546875
      ],
      "section_hierarchy": {
        "2": "/page/0/SectionHeader/0"
      },
      "images": {}
    },
    {
      "id": "/page/0/Form/1",
      "block_type": "Form",
      "html": "<table><tbody><tr><th></th><th></th><th></th></tr><tr><td>INZAKE :</td><td></td><td></td></tr><tr><td>Galloo n.v.</td><td></td><td></td></tr><tr><th>en :</th><th></th><th></th></tr><tr><td>Galloometal n.v.</td><td></td><td></td></tr><tr><td>en :</td><td></td><td></td></tr></tbody></table>",
      "page": 136,
      "polygon": [
        [
          71.58984375,
          95.7939453125
        ],
        [
          317.20703125,
          95.7939453125
        ],
        [
          317.20703125,
          215.69512939453125
        ],
        [
          71.58984375,
          215.69512939453125
        ]
      ],
      "bbox": [
        71.58984375,
        95.7939453125,
        317.20703125,
        215.69512939453125
      ],
      "section_hierarchy": {
        "2": "/page/0/SectionHeader/0"
      },
      "images": {}
    },
    {
      "id": "/page/0/Text/2",
      "block_type": "Text",
      "html": "<p block-type=\"Text\">Trade Arbed s.a.</p>",
      "page": 136,
      "polygon": [
        [
          71.0078125,
          229.19512939453125
        ],
        [
          146.27520751953125,
          229.19512939453125
        ],
        [
          146.27520751953125,
          240.44512939453125
        ],
        [
          71.0078125,
          240.44512939453125
        ]
      ],
      "bbox": [
        71.0078125,
        229.19512939453125,
        146.27520751953125,
        240.44512939453125
      ],
      "section_hierarchy": {
        "2": "/page/0/SectionHeader/0"
      },
      "images": {}
    },
    {
      "id": "/page/0/Text/3",
      "block_type": "Text",
      "html": "<p block-type=\"Text\">Gelet op de Wet op de Bescherming van de Economische Mededinging, zoals gecoördineerd op 1 juli  1999 (W.B.E.M.).</p>",
      "page": 136,
      "polygon": [
        [
          71.0078125,
          253.2578125
        ],
        [
          528.41748046875,
          253.2578125
        ],
        [
          528.41748046875,
          277.94512939453125
        ],
        [
          71.0078125,
          277.94512939453125
        ]
      ],
      "bbox": [
        71.0078125,
        253.2578125,
        528.41748046875,
        277.94512939453125
      ],
      "section_hierarchy": {
        "2": "/page/0/SectionHeader/0"
      },
      "images": {}
    },
    {
      "id": "/page/0/Text/4",
      "block_type": "Text",
      "html": "<p block-type=\"Text\">Gezien de aanmelding aan het Secretariaat van de Raad voor de Mededinging van een concentratie op  11 maart 2002.</p>",
      "page": 136,
      "polygon": [
        [
          71.0078125,
          291.44512939453125
        ],
        [
          528.5657348632812,
          291.44512939453125
        ],
        [
          528.5657348632812,
          315.44512939453125
        ],
        [
          71.0078125,
          315.44512939453125
        ]
      ],
      "bbox": [
        71.0078125,
        291.44512939453125,
        528.5657348632812,
        315.44512939453125
      ],
      "section_hierarchy": {
        "2": "/page/0/SectionHeader/0"
      },
      "images": {}
    },
    {
      "id": "/page/0/Text/5",
      "block_type": "Text",
      "html": "<p block-type=\"Text\">Gezien de mededeling voor onderzoek door het Secretariaat van de Raad aan het korps van  verslaggevers conform artikel 32 bis § 1 W.B.E.M. op 12 maart 2002.</p>",
      "page": 136,
      "polygon": [
        [
          71.0078125,
          328.94512939453125
        ],
        [
          526.453125,
          328.94512939453125
        ],
        [
          526.453125,
          352.19512939453125
        ],
        [
          71.0078125,
          352.19512939453125
        ]
      ],
      "bbox": [
        71.0078125,
        328.94512939453125,
        526.453125,
        352.19512939453125
      ],
      "section_hierarchy": {
        "2": "/page/0/SectionHeader/0"
      },
      "images": {}
    },
    {
      "id": "/page/0/Text/6",
      "block_type": "Text",
      "html": "<p block-type=\"Text\">Gezien de stukken van het dossier.</p>",
      "page": 136,
      "polygon": [
        [
          71.58984375,
          365.69512939453125
        ],
        [
          225.14260864257812,
          365.69512939453125
        ],
        [
          225.14260864257812,
          376.94512939453125
        ],
        [
          71.58984375,
          376.94512939453125
        ]
      ],
      "bbox": [
        71.58984375,
        365.69512939453125,
        225.14260864257812,
        376.94512939453125
      ],
      "section_hierarchy": {
        "2": "/page/0/SectionHeader/0"
      },
      "images": {}
    },
    {
      "id": "/page/0/Text/7",
      "block_type": "Text",
      "html": "<p block-type=\"Text\">Gezien het onderzoeksdossier van de Dienst voor de Mededinging, zoals dit op 8 april 2002 werd  overgemaakt aan de verslaggever.</p>",
      "page": 136,
      "polygon": [
        [
          71.0078125,
          389.3427734375
        ],
        [
          526.4356689453125,
          389.3427734375
        ],
        [
          526.4356689453125,
          414.44512939453125
        ],
        [
          71.0078125,
          414.44512939453125
        ]
      ],
      "bbox": [
        71.0078125,
        389.3427734375,
        526.4356689453125,
        414.44512939453125
      ],
      "section_hierarchy": {
        "2": "/page/0/SectionHeader/0"
      },
      "images": {}
    },
    {
      "id": "/page/0/Text/8",
      "block_type": "Text",
      "html": "<p block-type=\"Text\">Gezien het gemotiveerd verslag van de verslaggever zoals dit op 8 april 2002 werd opgesteld en  overgemaakt aan de Raad.</p>",
      "page": 136,
      "polygon": [
        [
          71.0078125,
          427.94512939453125
        ],
        [
          527.1130981445312,
          427.94512939453125
        ],
        [
          527.1130981445312,
          452.24609375
        ],
        [
          71.0078125,
          452.24609375
        ]
      ],
      "bbox": [
        71.0078125,
        427.94512939453125,
        527.1130981445312,
        452.24609375
      ],
      "section_hierarchy": {
        "2": "/page/0/SectionHeader/0"
      },
      "images": {}
    },
    {
      "id": "/page/0/Text/9",
      "block_type": "Text",
      "html": "<p block-type=\"Text\">Gezien de memorie van antwoord op 22 april 2002 neergelegd bij de Raad namens de aanmeldende  partijen.</p>",
      "page": 136,
      "polygon": [
        [
          71.0078125,
          465.40234375
        ],
        [
          527.8123779296875,
          465.40234375
        ],
        [
          527.8123779296875,
          489.44512939453125
        ],
        [
          71.0078125,
          489.44512939453125
        ]
      ],
      "bbox": [
        71.0078125,
        465.40234375,
        527.8123779296875,
        489.44512939453125
      ],
      "section_hierarchy": {
        "2": "/page/0/SectionHeader/0"
      },
      "images": {}
    },
    {
      "id": "/page/0/Text/10",
      "block_type": "Text",
      "html": "<p block-type=\"Text\">Gehoord de verslaggever, de heer Bert Stulens, ter zitting van 25 april 2002.</p>",
      "page": 136,
      "polygon": [
        [
          71.0078125,
          501.9931640625
        ],
        [
          406.6720275878906,
          501.9931640625
        ],
        [
          406.6720275878906,
          513.4451293945312
        ],
        [
          71.0078125,
          513.4451293945312
        ]
      ],
      "bbox": [
        71.0078125,
        501.9931640625,
        406.6720275878906,
        513.4451293945312
      ],
      "section_hierarchy": {
        "2": "/page/0/SectionHeader/0"
      },
      "images": {}
    },
    {
      "id": "/page/0/Text/11",
      "block_type": "Text",
      "html": "<p block-type=\"Text\">Gehoord namens de Dienst, de heren Johan Isselée en Erwin Verhaeren.</p>",
      "page": 136,
      "polygon": [
        [
          72.0,
          526.9451293945312
        ],
        [
          390.13629150390625,
          526.9451293945312
        ],
        [
          390.13629150390625,
          538.1951293945312
        ],
        [
          72.0,
          538.1951293945312
        ]
      ],
      "bbox": [
        72.0,
        526.9451293945312,
        390.13629150390625,
        538.1951293945312
      ],
      "section_hierarchy": {
        "2": "/page/0/SectionHeader/0"
      },
      "images": {}
    },
    {
      "id": "/page/0/Text/12",
      "block_type": "Text",
      "html": "<p block-type=\"Text\">Gehoord de aanmeldende partijen bij monde van de heer Patrick De Jonghe, de heer Pierre Vandeputte  van de n.v. Galloo en meerster Koen De Bock voor de n.v. Galloo en de n.v. Galloometal.</p>",
      "page": 136,
      "polygon": [
        [
          71.0078125,
          551.3291015625
        ],
        [
          528.7274780273438,
          551.3291015625
        ],
        [
          528.7274780273438,
          575.6951293945312
        ],
        [
          71.0078125,
          575.6951293945312
        ]
      ],
      "bbox": [
        71.0078125,
        551.3291015625,
        528.7274780273438,
        575.6951293945312
      ],
      "section_hierarchy": {
        "2": "/page/0/SectionHeader/0"
      },
      "images": {}
    },
    {
      "id": "/page/0/Text/13",
      "block_type": "Text",
      "html": "<p block-type=\"Text\">Gelet op de Wet van 15 juni 1935 op het taalgebruik in gerechtszaken van toepassing overeenkomstig  artikel 54 bis W.B.E.M..</p>",
      "page": 136,
      "polygon": [
        [
          71.0078125,
          589.1951293945312
        ],
        [
          528.37109375,
          589.1951293945312
        ],
        [
          528.37109375,
          613.1951293945312
        ],
        [
          71.0078125,
          613.1951293945312
        ]
      ],
      "bbox": [
        71.0078125,
        589.1951293945312,
        528.37109375,
        613.1951293945312
      ],
      "section_hierarchy": {
        "2": "/page/0/SectionHeader/0"
      },
      "images": {}
    },
    {
      "id": "/page/0/SectionHeader/14",
      "block_type": "SectionHeader",
      "html": "<h2>1. De aanmeldende en betrokken partijen :</h2>",
      "page": 136,
      "polygon": [
        [
          71.58984375,
          634.2775268554688
        ],
        [
          299.201416015625,
          634.2775268554688
        ],
        [
          299.201416015625,
          646.2775268554688
        ],
        [
          71.58984375,
          646.2775268554688
        ]
      ],
      "bbox": [
        71.58984375,
        634.2775268554688,
        299.201416015625,
        646.2775268554688
      ],
      "section_hierarchy": {
        "2": "/page/0/SectionHeader/14"
      },
      "images": {}
    },
    {
      "id": "/page/0/Text/15",
      "block_type": "Text",
      "html": "<p block-type=\"Text\">Als koper treden op de n.v. Galloo en de n.v. Galloometal.</p>",
      "page": 136,
      "polygon": [
        [
          71.58984375,
          655.1951293945312
        ],
        [
          328.6844787597656,
          655.1951293945312
        ],
        [
          328.6844787597656,
          666.4451293945312
        ],
        [
          71.58984375,
          666.4451293945312
        ]
      ],
      "bbox": [
        71.58984375,
        655.1951293945312,
        328.6844787597656,
        666.4451293945312
      ],
      "section_hierarchy": {
        "2": "/page/0/SectionHeader/14"
      },
      "images": {}
    },
    {
      "id": "/page/0/Text/16",
      "block_type": "Text",
      "html": "<p block-type=\"Text\">De n.v. Galloo is gevestigd in België te 8390 Menen, Wervikstraat 320, en is actief in de aan- en  verkoop, bewerken en verwerken van alle metalen, verder ondermeer in het uitvoeren van alle  grondwerken en in het verzorgen van tolformaliteiten inzake invoer, uitvoer en doorvoer.</p>",
      "page": 136,
      "polygon": [
        [
          71.0078125,
          679.6025390625
        ],
        [
          527.0625610351562,
          679.6025390625
        ],
        [
          527.0625610351562,
          716.6951217651367
        ],
        [
          71.0078125,
          716.6951217651367
        ]
      ],
      "bbox": [
        71.0078125,
        679.6025390625,
        527.0625610351562,
        716.6951217651367
      ],
      "section_hierarchy": {
        "2": "/page/0/SectionHeader/14"
      },
      "images": {}
    },
    {
      "id": "/page/0/Text/17",
      "block_type": "Text",
      "html": "<p block-type=\"Text\" class=\"has-continuation\">De n.v. Galloometal is eveneens gevestigd op hetzelfde adres als de n.v. Galloo, namelijk in België  te 8390 Menen, Wervikstraat 320, en is actief in de recuperatie en het verwerken (zoals het zuiveren,  scheiden, smelten en gieten) van alle metalen, alsook de aankoop en verkoop ervan zowel in binnen-</p>",
      "page": 136,
      "polygon": [
        [
          71.0078125,
          729.4451217651367
        ],
        [
          528.453857421875,
          729.4451217651367
        ],
        [
          528.453857421875,
          767.99609375
        ],
        [
          71.0078125,
          767.99609375
        ]
      ],
      "bbox": [
        71.0078125,
        729.4451217651367,
        528.453857421875,
        767.99609375
      ],
      "section_hierarchy": {
        "2": "/page/0/SectionHeader/14"
      },
      "images": {}
    },
    {
      "id": "/page/1/Text/0",
      "block_type": "Text",
      "html": "<p block-type=\"Text\">als buitenland, verder inzake de verwerking tot tussen en/of eindproduct, alsmede inzake het dumpen,  recupereren en recycleren van alle afvalproducten.</p>",
      "page": 140,
      "polygon": [
        [
          71.0078125,
          71.69512939453125
        ],
        [
          528.5653076171875,
          71.69512939453125
        ],
        [
          528.5653076171875,
          94.9716796875
        ],
        [
          71.0078125,
          94.9716796875
        ]
      ],
      "bbox": [
        71.0078125,
        71.69512939453125,
        528.5653076171875,
        94.9716796875
      ],
      "section_hierarchy": {
        "2": "/page/0/SectionHeader/14"
      },
      "images": {}
    },
    {
      "id": "/page/1/Text/1",
      "block_type": "Text",
      "html": "<p block-type=\"Text\">Als verkoper treedt op de s.a. Arbed, gevestigd in Luxemburg, te 2930 Luxemburg, Avenue de la  Liberté 19, die actief is in de handel van ertsen, bewerkte en onbewerkte metalen, alle waren afkomstig van, bestemd voor of die van nut zijn in de metaal-, delfstof- of steenkoolverwerkende  industrie of aanverwante bedrijven.</p>",
      "page": 140,
      "polygon": [
        [
          71.0078125,
          108.44512939453125
        ],
        [
          527.8157958984375,
          108.44512939453125
        ],
        [
          527.8157958984375,
          157.94512939453125
        ],
        [
          71.0078125,
          157.94512939453125
        ]
      ],
      "bbox": [
        71.0078125,
        108.44512939453125,
        527.8157958984375,
        157.94512939453125
      ],
      "section_hierarchy": {
        "2": "/page/0/SectionHeader/14"
      },
      "images": {}
    },
    {
      "id": "/page/1/Text/2",
      "block_type": "Text",
      "html": "<p block-type=\"Text\">Als doelonderneming treedt op de n.v. Almetal Holding, gevestigd in België, te 9000 Gent, Scheepzatestraat 9.</p>",
      "page": 140,
      "polygon": [
        [
          71.0078125,
          171.44512939453125
        ],
        [
          525.874267578125,
          171.44512939453125
        ],
        [
          525.874267578125,
          195.44512939453125
        ],
        [
          71.0078125,
          195.44512939453125
        ]
      ],
      "bbox": [
        71.0078125,
        171.44512939453125,
        525.874267578125,
        195.44512939453125
      ],
      "section_hierarchy": {
        "2": "/page/0/SectionHeader/14"
      },
      "images": {}
    },
    {
      "id": "/page/1/Text/3",
      "block_type": "Text",
      "html": "<p block-type=\"Text\">De n.v. Almetal Holding groepeert en controleert via de n.v. Almetal Beheer, gevestigd op  hetzelfde adres, een aantal filialen die eveneens deel uitmaken van de concentratieoperatie.</p>",
      "page": 140,
      "polygon": [
        [
          69.84375,
          208.19512939453125
        ],
        [
          527.170654296875,
          208.19512939453125
        ],
        [
          527.170654296875,
          232.19512939453125
        ],
        [
          69.84375,
          232.19512939453125
        ]
      ],
      "bbox": [
        69.84375,
        208.19512939453125,
        527.170654296875,
        232.19512939453125
      ],
      "section_hierarchy": {
        "2": "/page/0/SectionHeader/14"
      },
      "images": {}
    },
    {
      "id": "/page/1/SectionHeader/4",
      "block_type": "SectionHeader",
      "html": "<h3>Deze filialen zijn :</h3>",
      "page": 140,
      "polygon": [
        [
          71.298828125,
          245.69512939453125
        ],
        [
          154.63235473632812,
          245.69512939453125
        ],
        [
          154.63235473632812,
          256.94512939453125
        ],
        [
          71.298828125,
          256.94512939453125
        ]
      ],
      "bbox": [
        71.298828125,
        245.69512939453125,
        154.63235473632812,
        256.94512939453125
      ],
      "section_hierarchy": {
        "2": "/page/0/SectionHeader/14",
        "3": "/page/1/SectionHeader/4"
      },
      "images": {}
    },
    {
      "id": "/page/1/ListGroup/140",
      "block_type": "ListGroup",
      "html": "<p block-type=\"ListGroup\"><ul><li block-type=\"ListItem\"> Van Heyghen Recycling n.v., gevestigd in België, 9000 Gent, Scheepzatestraat 9.</li><li block-type=\"ListItem\"> D'Hollander Recycling n.v., gevestigd in België, 9000 Gent, Scheepzatestraat 9.</li><li block-type=\"ListItem\"> Retra n.v., gevestigd in België, 9000 Gent, Scheepzatestraat 5.</li><li block-type=\"ListItem\"> Nefer n.v., gevestigd in België, 3690 Zutendaal, Tiendenstraat 8.</li><li block-type=\"ListItem\"> Almetal Deutschland GmbH, gevestigd in Duitsland, 58456 Witten, Wittener Strasze 168.</li></ul></p>",
      "page": 140,
      "polygon": [
        [
          68.6796875,
          265.1806640625
        ],
        [
          449.8791198730469,
          265.1806640625
        ],
        [
          449.8791198730469,
          333.1524353027344
        ],
        [
          68.6796875,
          333.1524353027344
        ]
      ],
      "bbox": [
        68.6796875,
        265.1806640625,
        449.8791198730469,
        333.1524353027344
      ],
      "section_hierarchy": {
        "2": "/page/0/SectionHeader/14",
        "3": "/page/1/SectionHeader/4"
      },
      "images": {}
    },
    {
      "id": "/page/1/Text/10",
      "block_type": "Text",
      "html": "<p block-type=\"Text\">Al deze ondernemingen zijn actief op het gebied van de handel in schroot en metalen, alsook op het  vlak van afbraak- en slopingswerken.</p>",
      "page": 140,
      "polygon": [
        [
          71.0078125,
          343.19512939453125
        ],
        [
          528.5213623046875,
          343.19512939453125
        ],
        [
          528.5213623046875,
          367.19512939453125
        ],
        [
          71.0078125,
          367.19512939453125
        ]
      ],
      "bbox": [
        71.0078125,
        343.19512939453125,
        528.5213623046875,
        367.19512939453125
      ],
      "section_hierarchy": {
        "2": "/page/0/SectionHeader/14",
        "3": "/page/1/SectionHeader/4"
      },
      "images": {}
    },
    {
      "id": "/page/1/Text/11",
      "block_type": "Text",
      "html": "<p block-type=\"Text\">De n.v. Van Heyghen Recycling richt zich samen met haar tradingdivisie Ferinter te Luik ondermeer  op export van ferroschroot vanuit de Gentse zeehaven.</p>",
      "page": 140,
      "polygon": [
        [
          71.0078125,
          379.94512939453125
        ],
        [
          527.8934326171875,
          379.94512939453125
        ],
        [
          527.8934326171875,
          404.5546875
        ],
        [
          71.0078125,
          404.5546875
        ]
      ],
      "bbox": [
        71.0078125,
        379.94512939453125,
        527.8934326171875,
        404.5546875
      ],
      "section_hierarchy": {
        "2": "/page/0/SectionHeader/14",
        "3": "/page/1/SectionHeader/4"
      },
      "images": {}
    },
    {
      "id": "/page/1/Text/12",
      "block_type": "Text",
      "html": "<p block-type=\"Text\">De n.v. Retra, alsook haar divisies Renofe en Besri, zijn gespecialiseerd in de recuperatie van nonferrometalen en elektronicaschroot. De n.v. Retra beschikt over een shredderinstallatie.</p>",
      "page": 140,
      "polygon": [
        [
          71.0078125,
          416.4775390625
        ],
        [
          524.9966430664062,
          416.4775390625
        ],
        [
          524.9966430664062,
          441.44512939453125
        ],
        [
          71.0078125,
          441.44512939453125
        ]
      ],
      "bbox": [
        71.0078125,
        416.4775390625,
        524.9966430664062,
        441.44512939453125
      ],
      "section_hierarchy": {
        "2": "/page/0/SectionHeader/14",
        "3": "/page/1/SectionHeader/4"
      },
      "images": {}
    },
    {
      "id": "/page/1/Text/13",
      "block_type": "Text",
      "html": "<p block-type=\"Text\">De n.v. Nefer, samen met de Duitse tradingvennootschap Almetal Deutschland (Nefer bezit een  participatie van 50 % van de aandelen) hebben dezelfde specialisaties als Retra, met uitzondering van  de shredderinstallatie.</p>",
      "page": 140,
      "polygon": [
        [
          71.0078125,
          454.94512939453125
        ],
        [
          528.4095458984375,
          454.94512939453125
        ],
        [
          528.4095458984375,
          491.69512939453125
        ],
        [
          71.0078125,
          491.69512939453125
        ]
      ],
      "bbox": [
        71.0078125,
        454.94512939453125,
        528.4095458984375,
        491.69512939453125
      ],
      "section_hierarchy": {
        "2": "/page/0/SectionHeader/14",
        "3": "/page/1/SectionHeader/4"
      },
      "images": {}
    },
    {
      "id": "/page/1/Text/14",
      "block_type": "Text",
      "html": "<p block-type=\"Text\">De genoemde vennootschappen zijn ondernemingen in de zin van artikel 1 W.B.E.M..</p>",
      "page": 140,
      "polygon": [
        [
          72.0,
          504.44512939453125
        ],
        [
          452.405029296875,
          504.44512939453125
        ],
        [
          452.405029296875,
          515.6951293945312
        ],
        [
          72.0,
          515.6951293945312
        ]
      ],
      "bbox": [
        72.0,
        504.44512939453125,
        452.405029296875,
        515.6951293945312
      ],
      "section_hierarchy": {
        "2": "/page/0/SectionHeader/14",
        "3": "/page/1/SectionHeader/4"
      },
      "images": {}
    },
    {
      "id": "/page/1/SectionHeader/15",
      "block_type": "SectionHeader",
      "html": "<h2>2. De aangemelde operatie :</h2>",
      "page": 140,
      "polygon": [
        [
          71.58984375,
          536.7775268554688
        ],
        [
          222.7209930419922,
          536.7775268554688
        ],
        [
          222.7209930419922,
          548.7775268554688
        ],
        [
          71.58984375,
          548.7775268554688
        ]
      ],
      "bbox": [
        71.58984375,
        536.7775268554688,
        222.7209930419922,
        548.7775268554688
      ],
      "section_hierarchy": {
        "2": "/page/1/SectionHeader/15"
      },
      "images": {}
    },
    {
      "id": "/page/1/Text/16",
      "block_type": "Text",
      "html": "<p block-type=\"Text\">Ten gevolge van een overeenkomst van koop en verkoop van aandelen, afgesloten op 19  februari 2002, verkrijgen de n.v. Galloo en de n.v. Galloometal van de s.a. Trade Arbed alle  aandelen van de holding Almetal Holding.</p>",
      "page": 140,
      "polygon": [
        [
          69.84375,
          557.9072265625
        ],
        [
          527.3631591796875,
          557.9072265625
        ],
        [
          527.3631591796875,
          594.4451293945312
        ],
        [
          69.84375,
          594.4451293945312
        ]
      ],
      "bbox": [
        69.84375,
        557.9072265625,
        527.3631591796875,
        594.4451293945312
      ],
      "section_hierarchy": {
        "2": "/page/1/SectionHeader/15"
      },
      "images": {}
    },
    {
      "id": "/page/1/Text/17",
      "block_type": "Text",
      "html": "<p block-type=\"Text\">Hierdoor verwerven de kopers de directe zeggenschap over de n.v. Almetal Holding en haar  filialen. De kopers worden de enige eigenaars van de activiteiten van de n.v. Almetal op Vlaams  grondgebied. De n.v. Galloo verwerft 70 % van de aandelen en de n.v. Galloometal de overige 30 %.</p>",
      "page": 140,
      "polygon": [
        [
          71.0078125,
          607.9451293945312
        ],
        [
          527.101806640625,
          607.9451293945312
        ],
        [
          527.101806640625,
          645.8896484375
        ],
        [
          71.0078125,
          645.8896484375
        ]
      ],
      "bbox": [
        71.0078125,
        607.9451293945312,
        527.101806640625,
        645.8896484375
      ],
      "section_hierarchy": {
        "2": "/page/1/SectionHeader/15"
      },
      "images": {}
    },
    {
      "id": "/page/1/Text/18",
      "block_type": "Text",
      "html": "<p block-type=\"Text\">De gemelde transactie is een concentratie in de zin van artikel 9 § 1,b van de W.B.E.M..</p>",
      "page": 140,
      "polygon": [
        [
          71.0078125,
          658.1951293945312
        ],
        [
          463.65472412109375,
          658.1951293945312
        ],
        [
          463.65472412109375,
          669.4451293945312
        ],
        [
          71.0078125,
          669.4451293945312
        ]
      ],
      "bbox": [
        71.0078125,
        658.1951293945312,
        463.65472412109375,
        669.4451293945312
      ],
      "section_hierarchy": {
        "2": "/page/1/SectionHeader/15"
      },
      "images": {}
    },
    {
      "id": "/page/1/SectionHeader/19",
      "block_type": "SectionHeader",
      "html": "<h2>3. De aanmeldingstermijn :</h2>",
      "page": 140,
      "polygon": [
        [
          70.42578125,
          690.5275268554688
        ],
        [
          213.7476043701172,
          690.5275268554688
        ],
        [
          213.7476043701172,
          702.5275268554688
        ],
        [
          70.42578125,
          702.5275268554688
        ]
      ],
      "bbox": [
        70.42578125,
        690.5275268554688,
        213.7476043701172,
        702.5275268554688
      ],
      "section_hierarchy": {
        "2": "/page/1/SectionHeader/19"
      },
      "images": {}
    },
    {
      "id": "/page/1/Text/20",
      "block_type": "Text",
      "html": "<p block-type=\"Text\">De overeenkomst die het voorwerp uitmaakt van de aanmelding, namelijk de overeenkomst van koop  en verkoop van aandelen werd op 19 februari 2002 ondertekend en op 11 maart 2002 aangemeld.</p>",
      "page": 140,
      "polygon": [
        [
          71.0078125,
          711.4451293945312
        ],
        [
          528.445556640625,
          711.4451293945312
        ],
        [
          528.445556640625,
          735.5166015625
        ],
        [
          71.0078125,
          735.5166015625
        ]
      ],
      "bbox": [
        71.0078125,
        711.4451293945312,
        528.445556640625,
        735.5166015625
      ],
      "section_hierarchy": {
        "2": "/page/1/SectionHeader/19"
      },
      "images": {}
    },
    {
      "id": "/page/2/Text/0",
      "block_type": "Text",
      "html": "<p block-type=\"Text\">De aanmelding van de concentratie moet dan ook conform artikel 12 § 1 van de W.B.E.M. als tijdig  beoordeeld worden.</p>",
      "page": 134,
      "polygon": [
        [
          71.0078125,
          71.1259765625
        ],
        [
          528.3125,
          71.1259765625
        ],
        [
          528.3125,
          94.94512939453125
        ],
        [
          71.0078125,
          94.94512939453125
        ]
      ],
      "bbox": [
        71.0078125,
        71.1259765625,
        528.3125,
        94.94512939453125
      ],
      "section_hierarchy": {
        "2": "/page/1/SectionHeader/19"
      },
      "images": {}
    },
    {
      "id": "/page/2/SectionHeader/1",
      "block_type": "SectionHeader",
      "html": "<h2>4. De omzetdrempels :</h2>",
      "page": 134,
      "polygon": [
        [
          70.716796875,
          116.02752685546875
        ],
        [
          191.98391723632812,
          116.02752685546875
        ],
        [
          191.98391723632812,
          128.02752685546875
        ],
        [
          70.716796875,
          128.02752685546875
        ]
      ],
      "bbox": [
        70.716796875,
        116.02752685546875,
        191.98391723632812,
        128.02752685546875
      ],
      "section_hierarchy": {
        "2": "/page/2/SectionHeader/1"
      },
      "images": {}
    },
    {
      "id": "/page/2/Text/2",
      "block_type": "Text",
      "html": "<p block-type=\"Text\">De concentratie valt onder het toepassingsgebied van de W.B.E.M. vermits de omzetdrempels  zoals voorzien in artikel 11 § 1 en artikel 46 van de W.B.E.M. werden bereikt.</p>",
      "page": 134,
      "polygon": [
        [
          71.0078125,
          137.69512939453125
        ],
        [
          528.1099853515625,
          137.69512939453125
        ],
        [
          528.1099853515625,
          161.69512939453125
        ],
        [
          71.0078125,
          161.69512939453125
        ]
      ],
      "bbox": [
        71.0078125,
        137.69512939453125,
        528.1099853515625,
        161.69512939453125
      ],
      "section_hierarchy": {
        "2": "/page/2/SectionHeader/1"
      },
      "images": {}
    },
    {
      "id": "/page/2/Text/3",
      "block_type": "Text",
      "html": "<p block-type=\"Text\">Uit de ons verstrekte gegevens blijkt immers dat de Belgische omzet van de kopers, de n.v. Galloo en  de n.v. Galloometal, en de Belgische omzet van de doelonderneming, namelijk de n.v. Almetal  Holding, de n.v. Almetal Beheer en de vijf hierboven vernoemde filialen, de drempels voorzien in  artikel 11 § 1 W.B.E.M. overschrijden.</p>",
      "page": 134,
      "polygon": [
        [
          71.0078125,
          174.44512939453125
        ],
        [
          528.412841796875,
          174.44512939453125
        ],
        [
          528.412841796875,
          223.94512939453125
        ],
        [
          71.0078125,
          223.94512939453125
        ]
      ],
      "bbox": [
        71.0078125,
        174.44512939453125,
        528.412841796875,
        223.94512939453125
      ],
      "section_hierarchy": {
        "2": "/page/2/SectionHeader/1"
      },
      "images": {}
    },
    {
      "id": "/page/2/SectionHeader/4",
      "block_type": "SectionHeader",
      "html": "<h1>5. De marktafbakening en marktaandelen :</h1>",
      "page": 134,
      "polygon": [
        [
          70.42578125,
          245.02752685546875
        ],
        [
          299.2093505859375,
          245.02752685546875
        ],
        [
          299.2093505859375,
          257.369140625
        ],
        [
          70.42578125,
          257.369140625
        ]
      ],
      "bbox": [
        70.42578125,
        245.02752685546875,
        299.2093505859375,
        257.369140625
      ],
      "section_hierarchy": {
        "1": "/page/2/SectionHeader/4"
      },
      "images": {}
    },
    {
      "id": "/page/2/SectionHeader/5",
      "block_type": "SectionHeader",
      "html": "<h3>a. Over de relevante productmarkt :</h3>",
      "page": 134,
      "polygon": [
        [
          70.42578125,
          272.63519287109375
        ],
        [
          245.3529052734375,
          272.63519287109375
        ],
        [
          245.3529052734375,
          283.88519287109375
        ],
        [
          70.42578125,
          283.88519287109375
        ]
      ],
      "bbox": [
        70.42578125,
        272.63519287109375,
        245.3529052734375,
        283.88519287109375
      ],
      "section_hierarchy": {
        "1": "/page/2/SectionHeader/4",
        "3": "/page/2/SectionHeader/5"
      },
      "images": {}
    },
    {
      "id": "/page/2/Text/6",
      "block_type": "Text",
      "html": "<p block-type=\"Text\">De concentratie heeft betrekking op de schrootmarkt in metalen, onder te verdelen in twee deelmarkten, namelijk de markt van de recuperatie van ferrometalen en de markt van de recuperatie  van non-ferrometalen, waarbij elk van deze deelmarkten kan bekeken worden enerzijds langs de  aankoopzijde, anderzijds langs de verkoopzijde.</p>",
      "page": 134,
      "polygon": [
        [
          71.0078125,
          293.69512939453125
        ],
        [
          527.8746337890625,
          293.69512939453125
        ],
        [
          527.8746337890625,
          343.2958984375
        ],
        [
          71.0078125,
          343.2958984375
        ]
      ],
      "bbox": [
        71.0078125,
        293.69512939453125,
        527.8746337890625,
        343.2958984375
      ],
      "section_hierarchy": {
        "1": "/page/2/SectionHeader/4",
        "3": "/page/2/SectionHeader/5"
      },
      "images": {}
    },
    {
      "id": "/page/2/Text/7",
      "block_type": "Text",
      "html": "<p block-type=\"Text\">Voor wat de recuperatie van ferrometalen betreft moet vastgesteld worden dat voor wat de aankoop  betreft (aankoopzijde) het schroot lokaal wordt aangekocht bij ofwel lokale schroothandelaars, ofwel  bij de containerparken van intercommunales, ofwel bij autokerkhoven, waarna de verwerkte ferrometalen als secondaire grondstoffen aan de staalbedrijven worden verkocht (verkoopzijde), met  dien verstande dat de recuperatiebedrijven die in het binnenland zijn gelegen voornamelijk aan Europese staalbedrijven verkopen, terwijl de bedrijven die in het havengebied zijn gelegen tevens  kunnen exporteren en verkopen aan buiten Europa gelegen staalbedrijven.</p>",
      "page": 134,
      "polygon": [
        [
          71.0078125,
          356.4521484375
        ],
        [
          528.560302734375,
          356.4521484375
        ],
        [
          528.560302734375,
          443.69512939453125
        ],
        [
          71.0078125,
          443.69512939453125
        ]
      ],
      "bbox": [
        71.0078125,
        356.4521484375,
        528.560302734375,
        443.69512939453125
      ],
      "section_hierarchy": {
        "1": "/page/2/SectionHeader/4",
        "3": "/page/2/SectionHeader/5"
      },
      "images": {}
    },
    {
      "id": "/page/2/Text/8",
      "block_type": "Text",
      "html": "<p block-type=\"Text\">Voor wat de recuperatie van non-ferrometalen betreft moet vastgesteld worden dat voor wat de  aankoop betreft (aankoopzijde) het schroot wordt aangekocht op een markt die minder lokaal is  (gezien de hogere waarde ervan) bij ofwel schroothandelaars, hetzij flotatiebedrijven (die de  materialen in een niet metaalfractie en in een metaalfractie scheiden), waarna de verwerkte nonferrometalen (gezien hun hogere waarde) in de non-ferroindustrie worden verkocht.</p>",
      "page": 134,
      "polygon": [
        [
          71.0078125,
          456.357421875
        ],
        [
          527.1553955078125,
          456.357421875
        ],
        [
          527.1553955078125,
          518.6951293945312
        ],
        [
          71.0078125,
          518.6951293945312
        ]
      ],
      "bbox": [
        71.0078125,
        456.357421875,
        527.1553955078125,
        518.6951293945312
      ],
      "section_hierarchy": {
        "1": "/page/2/SectionHeader/4",
        "3": "/page/2/SectionHeader/5"
      },
      "images": {}
    },
    {
      "id": "/page/2/SectionHeader/9",
      "block_type": "SectionHeader",
      "html": "<h2>b. Over de relevante geografische markt :</h2>",
      "page": 134,
      "polygon": [
        [
          71.58984375,
          538.1728515625
        ],
        [
          274.6033935546875,
          538.1728515625
        ],
        [
          274.6033935546875,
          550.1351928710938
        ],
        [
          71.58984375,
          550.1351928710938
        ]
      ],
      "bbox": [
        71.58984375,
        538.1728515625,
        274.6033935546875,
        550.1351928710938
      ],
      "section_hierarchy": {
        "1": "/page/2/SectionHeader/4",
        "2": "/page/2/SectionHeader/9"
      },
      "images": {}
    },
    {
      "id": "/page/2/Text/10",
      "block_type": "Text",
      "html": "<p block-type=\"Text\">De relevante geografische markt van de markt van de recuperatie van \"ferrometalen\" omvat volgens  de verslaggever langs de aankoopzijde minstens de drie Belgische provincies West Vlaanderen, Oost  Vlaanderen en Henegouwen, volgens de aanmeldende partijen zelfs gans België, en langs de verkoopzijde het gehele Belgische grondgebied, met zelfs een sterke Europese dimensie.</p>",
      "page": 134,
      "polygon": [
        [
          71.0078125,
          559.9451293945312
        ],
        [
          528.5601806640625,
          559.9451293945312
        ],
        [
          528.5601806640625,
          609.298828125
        ],
        [
          71.0078125,
          609.298828125
        ]
      ],
      "bbox": [
        71.0078125,
        559.9451293945312,
        528.5601806640625,
        609.298828125
      ],
      "section_hierarchy": {
        "1": "/page/2/SectionHeader/4",
        "2": "/page/2/SectionHeader/9"
      },
      "images": {}
    },
    {
      "id": "/page/2/Text/11",
      "block_type": "Text",
      "html": "<p block-type=\"Text\">De relevante geografische markt van de recuperatie van \"non-ferrometalen\" omvat langs de aankoopzijde het gehele Belgische grondgebied, met een Europese dimensie en langs de verkoopzijde  geheel België, zij het met een ruimere Europese tot zelfs mondiale dimensie.</p>",
      "page": 134,
      "polygon": [
        [
          71.0078125,
          622.1951293945312
        ],
        [
          529.0831298828125,
          622.1951293945312
        ],
        [
          529.0831298828125,
          659.0458984375
        ],
        [
          71.0078125,
          659.0458984375
        ]
      ],
      "bbox": [
        71.0078125,
        622.1951293945312,
        529.0831298828125,
        659.0458984375
      ],
      "section_hierarchy": {
        "1": "/page/2/SectionHeader/4",
        "2": "/page/2/SectionHeader/9"
      },
      "images": {}
    },
    {
      "id": "/page/2/SectionHeader/12",
      "block_type": "SectionHeader",
      "html": "<h3>c. Over de marktaandelen :</h3>",
      "page": 134,
      "polygon": [
        [
          71.298828125,
          679.1351776123047
        ],
        [
          204.14381408691406,
          679.1351776123047
        ],
        [
          204.14381408691406,
          690.3851776123047
        ],
        [
          71.298828125,
          690.3851776123047
        ]
      ],
      "bbox": [
        71.298828125,
        679.1351776123047,
        204.14381408691406,
        690.3851776123047
      ],
      "section_hierarchy": {
        "1": "/page/2/SectionHeader/4",
        "2": "/page/2/SectionHeader/9",
        "3": "/page/2/SectionHeader/12"
      },
      "images": {}
    },
    {
      "id": "/page/2/Text/13",
      "block_type": "Text",
      "html": "<p block-type=\"Text\">De aanmeldende partijen stellen met verwijzing naar onder meer marktaandeelcijfers dat er geen sprake is van een betrokken markt nu enerzijds de n.v. Galloo en de n.v. Galloometal en anderzijds de  doelonderneming, in het bijzonder de filialen, samen in België zowel langs de aankoopzijde als langs  de verkoopzijde van respectievelijk de ferro en de non-ferrometalen een marktaandeel ver beneden de  25 % behalen.</p>",
      "page": 134,
      "polygon": [
        [
          71.0078125,
          700.1951293945312
        ],
        [
          529.22607421875,
          700.1951293945312
        ],
        [
          529.22607421875,
          761.6951217651367
        ],
        [
          71.0078125,
          761.6951217651367
        ]
      ],
      "bbox": [
        71.0078125,
        700.1951293945312,
        529.22607421875,
        761.6951217651367
      ],
      "section_hierarchy": {
        "1": "/page/2/SectionHeader/4",
        "2": "/page/2/SectionHeader/9",
        "3": "/page/2/SectionHeader/12"
      },
      "images": {}
    },
    {
      "id": "/page/3/Text/0",
      "block_type": "Text",
      "html": "<p block-type=\"Text\">Gezien het ontbreken van een aantal gegevens ontbreekt het in dit stadium de Raad aan de noodzakelijke, objectieve en betrouwbare beoordelingsgegevens om zich uit te spreken over de al dan  niet aanwezigheid van (een) betrokken markt(en) en over de al of niet dominante machtspositie van de  aanmeldende partijen op deze markt(en).</p>",
      "page": 77,
      "polygon": [
        [
          71.0078125,
          70.71484375
        ],
        [
          528.5632934570312,
          70.71484375
        ],
        [
          528.5632934570312,
          120.44512939453125
        ],
        [
          71.0078125,
          120.44512939453125
        ]
      ],
      "bbox": [
        71.0078125,
        70.71484375,
        528.5632934570312,
        120.44512939453125
      ],
      "section_hierarchy": {
        "1": "/page/2/SectionHeader/4",
        "2": "/page/2/SectionHeader/9",
        "3": "/page/2/SectionHeader/12"
      },
      "images": {}
    },
    {
      "id": "/page/3/Text/1",
      "block_type": "Text",
      "html": "<p block-type=\"Text\">Gezien ook de negatieve reacties van de concurrenten, stelt de Raad vast dat er ernstige twijfels  bestaan betreffende de toelaatbaarheid van de concentratie.</p>",
      "page": 77,
      "polygon": [
        [
          71.0078125,
          133.6181640625
        ],
        [
          527.4373168945312,
          133.6181640625
        ],
        [
          527.4373168945312,
          157.94512939453125
        ],
        [
          71.0078125,
          157.94512939453125
        ]
      ],
      "bbox": [
        71.0078125,
        133.6181640625,
        527.4373168945312,
        157.94512939453125
      ],
      "section_hierarchy": {
        "1": "/page/2/SectionHeader/4",
        "2": "/page/2/SectionHeader/9",
        "3": "/page/2/SectionHeader/12"
      },
      "images": {}
    },
    {
      "id": "/page/3/Text/2",
      "block_type": "Text",
      "html": "<p block-type=\"Text\">Een tweede faseonderzoek conform artikel 33 § 2.1b en artikel 34 § 1, alinea 1 W.B.E.M. is dan  ook noodzakelijk.</p>",
      "page": 77,
      "polygon": [
        [
          71.0078125,
          171.44512939453125
        ],
        [
          528.50146484375,
          171.44512939453125
        ],
        [
          528.50146484375,
          195.44512939453125
        ],
        [
          71.0078125,
          195.44512939453125
        ]
      ],
      "bbox": [
        71.0078125,
        171.44512939453125,
        528.50146484375,
        195.44512939453125
      ],
      "section_hierarchy": {
        "1": "/page/2/SectionHeader/4",
        "2": "/page/2/SectionHeader/9",
        "3": "/page/2/SectionHeader/12"
      },
      "images": {}
    },
    {
      "id": "/page/3/SectionHeader/3",
      "block_type": "SectionHeader",
      "html": "<h2>OM DEZE REDENEN,</h2>",
      "page": 77,
      "polygon": [
        [
          71.0078125,
          215.77752685546875
        ],
        [
          191.30999755859375,
          215.77752685546875
        ],
        [
          191.30999755859375,
          227.77752685546875
        ],
        [
          71.0078125,
          227.77752685546875
        ]
      ],
      "bbox": [
        71.0078125,
        215.77752685546875,
        191.30999755859375,
        227.77752685546875
      ],
      "section_hierarchy": {
        "1": "/page/2/SectionHeader/4",
        "2": "/page/3/SectionHeader/3"
      },
      "images": {}
    },
    {
      "id": "/page/3/SectionHeader/4",
      "block_type": "SectionHeader",
      "html": "<h2>De Raad voor de Mededinging,</h2>",
      "page": 77,
      "polygon": [
        [
          71.58984375,
          245.02752685546875
        ],
        [
          239.20883178710938,
          245.02752685546875
        ],
        [
          239.20883178710938,
          257.02752685546875
        ],
        [
          71.58984375,
          257.02752685546875
        ]
      ],
      "bbox": [
        71.58984375,
        245.02752685546875,
        239.20883178710938,
        257.02752685546875
      ],
      "section_hierarchy": {
        "1": "/page/2/SectionHeader/4",
        "2": "/page/3/SectionHeader/4"
      },
      "images": {}
    },
    {
      "id": "/page/3/ListGroup/77",
      "block_type": "ListGroup",
      "html": "<p block-type=\"ListGroup\"><ul><li block-type=\"ListItem\"> Stelt vast dat de betrokken concentratie onder het toepassingsgebied valt van de W.B.E.M..</li><li block-type=\"ListItem\"> Vooraleer over de al dan niet toelaatbaarheid van de concentratie te oordelen, verzoekt de Raad aan de  verslaggever om conform artikel 33 § 2.1,b uiterlijk op 14 mei 2002 een bijkomend verslag neer te leggen,  in het bijzonder betreffende de juiste geografische afbakening van de markt van de recuperatie van  ferrometalen langs de aankoopzijde en verder ter verificatie van de marktaandeelcijfers van de aanmeldende  partijen op de beide relevante productmarkten en dit telkens langs de aankoopzijde en langs de verkoopzijde.</li><li block-type=\"ListItem\"> Stelt de zaak voor verdere behandeling op donderdag 30 mei tweeduizend en twee, te vijftien uur.</li></ul></p>",
      "page": 77,
      "polygon": [
        [
          71.0078125,
          261.1524658203125
        ],
        [
          527.8092651367188,
          261.1524658203125
        ],
        [
          527.8092651367188,
          357.9024353027344
        ],
        [
          71.0078125,
          357.9024353027344
        ]
      ],
      "bbox": [
        71.0078125,
        261.1524658203125,
        527.8092651367188,
        357.9024353027344
      ],
      "section_hierarchy": {
        "1": "/page/2/SectionHeader/4",
        "2": "/page/3/SectionHeader/4"
      },
      "images": {}
    },
    {
      "id": "/page/3/Text/8",
      "block_type": "Text",
      "html": "<p block-type=\"Text\">Aldus uitgesproken op 25 april 2002, door de Kamer van de Raad voor de Mededinging samengesteld  uit : de heer Peter Poma, kamervoorzitter, de heren Paul Blondeel, Geert Zonnekeyn en Wouter  Devroe, leden.</p>",
      "page": 77,
      "polygon": [
        [
          69.84375,
          367.19512939453125
        ],
        [
          528.43505859375,
          367.19512939453125
        ],
        [
          528.43505859375,
          403.94512939453125
        ],
        [
          69.84375,
          403.94512939453125
        ]
      ],
      "bbox": [
        69.84375,
        367.19512939453125,
        528.43505859375,
        403.94512939453125
      ],
      "section_hierarchy": {
        "1": "/page/2/SectionHeader/4",
        "2": "/page/3/SectionHeader/4"
      },
      "images": {}
    }
  ],
  "page_info": {
    "0": {
      "bbox": [
        0.0,
        0.0,
        596.0,
        842.0
      ],
      "polygon": [
        [
          0.0,
          0.0
        ],
        [
          596.0,
          0.0
        ],
        [
          596.0,
          842.0
        ],
        [
          0.0,
          842.0
        ]
      ]
    },
    "1": {
      "bbox": [
        0.0,
        0.0,
        596.0,
        842.0
      ],
      "polygon": [
        [
          0.0,
          0.0
        ],
        [
          596.0,
          0.0
        ],
        [
          596.0,
          842.0
        ],
        [
          0.0,
          842.0
        ]
      ]
    },
    "2": {
      "bbox": [
        0.0,
        0.0,
        596.0,
        842.0
      ],
      "polygon": [
        [
          0.0,
          0.0
        ],
        [
          596.0,
          0.0
        ],
        [
          596.0,
          842.0
        ],
        [
          0.0,
          842.0
        ]
      ]
    },
    "3": {
      "bbox": [
        0.0,
        0.0,
        596.0,
        842.0
      ],
      "polygon": [
        [
          0.0,
          0.0
        ],
        [
          596.0,
          0.0
        ],
        [
          596.0,
          842.0
        ],
        [
          0.0,
          842.0
        ]
      ]
    }
  }
}