{
  "blocks": [
    {
      "id": "/page/0/SectionHeader/0",
      "block_type": "SectionHeader",
      "html": "<h1><i>Beslissing nr. 2002-C/C-13 van 8 februari 2002</i></h1>",
      "page": 187,
      "polygon": [
        [
          70.42578125,
          83.87109375
        ],
        [
          334.66796875,
          83.87109375
        ],
        [
          334.66796875,
          97.27752685546875
        ],
        [
          70.42578125,
          97.27752685546875
        ]
      ],
      "bbox": [
        70.42578125,
        83.87109375,
        334.66796875,
        97.27752685546875
      ],
      "section_hierarchy": {
        "1": "/page/0/SectionHeader/0"
      },
      "images": {}
    },
    {
      "id": "/page/0/SectionHeader/1",
      "block_type": "SectionHeader",
      "html": "<h4>Inzake:</h4>",
      "page": 187,
      "polygon": [
        [
          70.716796875,
          106.072265625
        ],
        [
          105.01575469970703,
          106.072265625
        ],
        [
          105.01575469970703,
          117.44512939453125
        ],
        [
          70.716796875,
          117.44512939453125
        ]
      ],
      "bbox": [
        70.716796875,
        106.072265625,
        105.01575469970703,
        117.44512939453125
      ],
      "section_hierarchy": {
        "1": "/page/0/SectionHeader/0",
        "4": "/page/0/SectionHeader/1"
      },
      "images": {}
    },
    {
      "id": "/page/0/Text/2",
      "block_type": "Text",
      "html": "<p block-type=\"Text\">NV BRICORAMA, 2031 Antwerpen, Noorderlaan 99 A</p>",
      "page": 187,
      "polygon": [
        [
          71.0078125,
          125.3955078125
        ],
        [
          297.6578369140625,
          125.3955078125
        ],
        [
          297.6578369140625,
          135.9024658203125
        ],
        [
          71.0078125,
          135.9024658203125
        ]
      ],
      "bbox": [
        71.0078125,
        125.3955078125,
        297.6578369140625,
        135.9024658203125
      ],
      "section_hierarchy": {
        "1": "/page/0/SectionHeader/0",
        "4": "/page/0/SectionHeader/1"
      },
      "images": {}
    },
    {
      "id": "/page/0/Text/3",
      "block_type": "Text",
      "html": "<p block-type=\"Text\">en</p>",
      "page": 187,
      "polygon": [
        [
          71.298828125,
          137.4024658203125
        ],
        [
          82.357421875,
          137.4024658203125
        ],
        [
          82.357421875,
          147.1524658203125
        ],
        [
          71.298828125,
          147.1524658203125
        ]
      ],
      "bbox": [
        71.298828125,
        137.4024658203125,
        82.357421875,
        147.1524658203125
      ],
      "section_hierarchy": {
        "1": "/page/0/SectionHeader/0",
        "4": "/page/0/SectionHeader/1"
      },
      "images": {}
    },
    {
      "id": "/page/0/Text/4",
      "block_type": "Text",
      "html": "<p block-type=\"Text\">NV POGAM, 9000 Gent, Maisstraat 62</p>",
      "page": 187,
      "polygon": [
        [
          70.42578125,
          148.6524658203125
        ],
        [
          230.8870086669922,
          148.6524658203125
        ],
        [
          230.8870086669922,
          158.4024658203125
        ],
        [
          70.42578125,
          158.4024658203125
        ]
      ],
      "bbox": [
        70.42578125,
        148.6524658203125,
        230.8870086669922,
        158.4024658203125
      ],
      "section_hierarchy": {
        "1": "/page/0/SectionHeader/0",
        "4": "/page/0/SectionHeader/1"
      },
      "images": {}
    },
    {
      "id": "/page/0/Text/5",
      "block_type": "Text",
      "html": "<p block-type=\"Text\">en</p>",
      "page": 187,
      "polygon": [
        [
          71.298828125,
          160.6524658203125
        ],
        [
          81.47699737548828,
          160.6524658203125
        ],
        [
          81.47699737548828,
          170.4024658203125
        ],
        [
          71.298828125,
          170.4024658203125
        ]
      ],
      "bbox": [
        71.298828125,
        160.6524658203125,
        81.47699737548828,
        170.4024658203125
      ],
      "section_hierarchy": {
        "1": "/page/0/SectionHeader/0",
        "4": "/page/0/SectionHeader/1"
      },
      "images": {}
    },
    {
      "id": "/page/0/Text/6",
      "block_type": "Text",
      "html": "<p block-type=\"Text\">NV TERBASSENWEI, 8680 Koekelare, Brouwerijstraat 14</p>",
      "page": 187,
      "polygon": [
        [
          68.6796875,
          171.4423828125
        ],
        [
          313.36126708984375,
          171.4423828125
        ],
        [
          313.36126708984375,
          181.6524658203125
        ],
        [
          68.6796875,
          181.6524658203125
        ]
      ],
      "bbox": [
        68.6796875,
        171.4423828125,
        313.36126708984375,
        181.6524658203125
      ],
      "section_hierarchy": {
        "1": "/page/0/SectionHeader/0",
        "4": "/page/0/SectionHeader/1"
      },
      "images": {}
    },
    {
      "id": "/page/0/Text/7",
      "block_type": "Text",
      "html": "<p block-type=\"Text\">en</p>",
      "page": 187,
      "polygon": [
        [
          71.880859375,
          183.1524658203125
        ],
        [
          81.47699737548828,
          183.1524658203125
        ],
        [
          81.47699737548828,
          192.9024658203125
        ],
        [
          71.880859375,
          192.9024658203125
        ]
      ],
      "bbox": [
        71.880859375,
        183.1524658203125,
        81.47699737548828,
        192.9024658203125
      ],
      "section_hierarchy": {
        "1": "/page/0/SectionHeader/0",
        "4": "/page/0/SectionHeader/1"
      },
      "images": {}
    },
    {
      "id": "/page/0/Text/8",
      "block_type": "Text",
      "html": "<p block-type=\"Text\">NV C.B. BOUWMARKTEN, 2440 Geel, Acaciastraat 25</p>",
      "page": 187,
      "polygon": [
        [
          71.0078125,
          194.4658203125
        ],
        [
          302.1456298828125,
          194.4658203125
        ],
        [
          302.1456298828125,
          204.9024658203125
        ],
        [
          71.0078125,
          204.9024658203125
        ]
      ],
      "bbox": [
        71.0078125,
        194.4658203125,
        302.1456298828125,
        204.9024658203125
      ],
      "section_hierarchy": {
        "1": "/page/0/SectionHeader/0",
        "4": "/page/0/SectionHeader/1"
      },
      "images": {}
    },
    {
      "id": "/page/0/Text/9",
      "block_type": "Text",
      "html": "<p block-type=\"Text\">en</p>",
      "page": 187,
      "polygon": [
        [
          71.298828125,
          206.4024658203125
        ],
        [
          82.357421875,
          206.4024658203125
        ],
        [
          82.357421875,
          216.1524658203125
        ],
        [
          71.298828125,
          216.1524658203125
        ]
      ],
      "bbox": [
        71.298828125,
        206.4024658203125,
        82.357421875,
        216.1524658203125
      ],
      "section_hierarchy": {
        "1": "/page/0/SectionHeader/0",
        "4": "/page/0/SectionHeader/1"
      },
      "images": {}
    },
    {
      "id": "/page/0/Text/10",
      "block_type": "Text",
      "html": "<p block-type=\"Text\">Mr. POLLET en Mrs. WYTINCK, 8680 Koekelare, Provinciebaan 25b</p>",
      "page": 187,
      "polygon": [
        [
          71.0078125,
          217.4892578125
        ],
        [
          356.12249755859375,
          217.4892578125
        ],
        [
          356.12249755859375,
          227.4024658203125
        ],
        [
          71.0078125,
          227.4024658203125
        ]
      ],
      "bbox": [
        71.0078125,
        217.4892578125,
        356.12249755859375,
        227.4024658203125
      ],
      "section_hierarchy": {
        "1": "/page/0/SectionHeader/0",
        "4": "/page/0/SectionHeader/1"
      },
      "images": {}
    },
    {
      "id": "/page/0/Text/11",
      "block_type": "Text",
      "html": "<p block-type=\"Text\">en</p>",
      "page": 187,
      "polygon": [
        [
          71.298828125,
          229.6524658203125
        ],
        [
          81.47699737548828,
          229.6524658203125
        ],
        [
          81.47699737548828,
          239.4024658203125
        ],
        [
          71.298828125,
          239.4024658203125
        ]
      ],
      "bbox": [
        71.298828125,
        229.6524658203125,
        81.47699737548828,
        239.4024658203125
      ],
      "section_hierarchy": {
        "1": "/page/0/SectionHeader/0",
        "4": "/page/0/SectionHeader/1"
      },
      "images": {}
    },
    {
      "id": "/page/0/Text/12",
      "block_type": "Text",
      "html": "<p block-type=\"Text\">NV BOUWMAR, 8680 Koekelare, Brouwerijstraat 14</p>",
      "page": 187,
      "polygon": [
        [
          69.84375,
          240.9024658203125
        ],
        [
          290.8902587890625,
          240.9024658203125
        ],
        [
          290.8902587890625,
          251.2021484375
        ],
        [
          69.84375,
          251.2021484375
        ]
      ],
      "bbox": [
        69.84375,
        240.9024658203125,
        290.8902587890625,
        251.2021484375
      ],
      "section_hierarchy": {
        "1": "/page/0/SectionHeader/0",
        "4": "/page/0/SectionHeader/1"
      },
      "images": {}
    },
    {
      "id": "/page/0/Text/13",
      "block_type": "Text",
      "html": "<p block-type=\"Text\">en</p>",
      "page": 187,
      "polygon": [
        [
          71.58984375,
          252.1524658203125
        ],
        [
          82.06640625,
          252.1524658203125
        ],
        [
          82.06640625,
          266.8251953125
        ],
        [
          71.58984375,
          266.8251953125
        ]
      ],
      "bbox": [
        71.58984375,
        252.1524658203125,
        82.06640625,
        266.8251953125
      ],
      "section_hierarchy": {
        "1": "/page/0/SectionHeader/0",
        "4": "/page/0/SectionHeader/1"
      },
      "images": {}
    },
    {
      "id": "/page/0/Text/14",
      "block_type": "Text",
      "html": "<p block-type=\"Text\">NV ROBO, 9000 Gent, Maisstraat 62</p>",
      "page": 187,
      "polygon": [
        [
          71.0078125,
          264.1524658203125
        ],
        [
          221.9150390625,
          264.1524658203125
        ],
        [
          221.9150390625,
          273.9024658203125
        ],
        [
          71.0078125,
          273.9024658203125
        ]
      ],
      "bbox": [
        71.0078125,
        264.1524658203125,
        221.9150390625,
        273.9024658203125
      ],
      "section_hierarchy": {
        "1": "/page/0/SectionHeader/0",
        "4": "/page/0/SectionHeader/1"
      },
      "images": {}
    },
    {
      "id": "/page/0/Text/15",
      "block_type": "Text",
      "html": "<p block-type=\"Text\">en</p>",
      "page": 187,
      "polygon": [
        [
          72.0,
          275.4024658203125
        ],
        [
          81.484375,
          275.4024658203125
        ],
        [
          81.484375,
          285.1524658203125
        ],
        [
          72.0,
          285.1524658203125
        ]
      ],
      "bbox": [
        72.0,
        275.4024658203125,
        81.484375,
        285.1524658203125
      ],
      "section_hierarchy": {
        "1": "/page/0/SectionHeader/0",
        "4": "/page/0/SectionHeader/1"
      },
      "images": {}
    },
    {
      "id": "/page/0/Text/16",
      "block_type": "Text",
      "html": "<p block-type=\"Text\">NV WABO, 9000 Gent, Maisstraat 62</p>",
      "page": 187,
      "polygon": [
        [
          70.42578125,
          286.6524658203125
        ],
        [
          225.24609375000003,
          286.6524658203125
        ],
        [
          225.24609375000003,
          296.4024658203125
        ],
        [
          70.42578125,
          296.4024658203125
        ]
      ],
      "bbox": [
        70.42578125,
        286.6524658203125,
        225.24609375000003,
        296.4024658203125
      ],
      "section_hierarchy": {
        "1": "/page/0/SectionHeader/0",
        "4": "/page/0/SectionHeader/1"
      },
      "images": {}
    },
    {
      "id": "/page/0/Text/17",
      "block_type": "Text",
      "html": "<p block-type=\"Text\">en</p>",
      "page": 187,
      "polygon": [
        [
          70.42578125,
          298.6524658203125
        ],
        [
          81.47699737548828,
          298.6524658203125
        ],
        [
          81.47699737548828,
          312.4609375
        ],
        [
          70.42578125,
          312.4609375
        ]
      ],
      "bbox": [
        70.42578125,
        298.6524658203125,
        81.47699737548828,
        312.4609375
      ],
      "section_hierarchy": {
        "1": "/page/0/SectionHeader/0",
        "4": "/page/0/SectionHeader/1"
      },
      "images": {}
    },
    {
      "id": "/page/0/Text/18",
      "block_type": "Text",
      "html": "<p block-type=\"Text\">NV MULTI HOBBY, 9000 Gent, Maisstraat 62</p>",
      "page": 187,
      "polygon": [
        [
          68.6796875,
          309.9024658203125
        ],
        [
          263.89520263671875,
          309.9024658203125
        ],
        [
          263.89520263671875,
          319.6524658203125
        ],
        [
          68.6796875,
          319.6524658203125
        ]
      ],
      "bbox": [
        68.6796875,
        309.9024658203125,
        263.89520263671875,
        319.6524658203125
      ],
      "section_hierarchy": {
        "1": "/page/0/SectionHeader/0",
        "4": "/page/0/SectionHeader/1"
      },
      "images": {}
    },
    {
      "id": "/page/0/Text/19",
      "block_type": "Text",
      "html": "<p block-type=\"Text\">en</p>",
      "page": 187,
      "polygon": [
        [
          71.298828125,
          321.1524658203125
        ],
        [
          81.47699737548828,
          321.1524658203125
        ],
        [
          81.47699737548828,
          330.9619140625
        ],
        [
          71.298828125,
          330.9619140625
        ]
      ],
      "bbox": [
        71.298828125,
        321.1524658203125,
        81.47699737548828,
        330.9619140625
      ],
      "section_hierarchy": {
        "1": "/page/0/SectionHeader/0",
        "4": "/page/0/SectionHeader/1"
      },
      "images": {}
    },
    {
      "id": "/page/0/Text/20",
      "block_type": "Text",
      "html": "<p block-type=\"Text\">BVBA GRUTO, 2200 Herentals, Hemeldonk 3</p>",
      "page": 187,
      "polygon": [
        [
          69.84375,
          333.017578125
        ],
        [
          261.66998291015625,
          333.017578125
        ],
        [
          261.66998291015625,
          342.9024353027344
        ],
        [
          69.84375,
          342.9024353027344
        ]
      ],
      "bbox": [
        69.84375,
        333.017578125,
        261.66998291015625,
        342.9024353027344
      ],
      "section_hierarchy": {
        "1": "/page/0/SectionHeader/0",
        "4": "/page/0/SectionHeader/1"
      },
      "images": {}
    },
    {
      "id": "/page/0/Text/21",
      "block_type": "Text",
      "html": "<p block-type=\"Text\">en</p>",
      "page": 187,
      "polygon": [
        [
          71.0078125,
          344.4024353027344
        ],
        [
          81.484375,
          344.4024353027344
        ],
        [
          81.484375,
          354.1524353027344
        ],
        [
          71.0078125,
          354.1524353027344
        ]
      ],
      "bbox": [
        71.0078125,
        344.4024353027344,
        81.484375,
        354.1524353027344
      ],
      "section_hierarchy": {
        "1": "/page/0/SectionHeader/0",
        "4": "/page/0/SectionHeader/1"
      },
      "images": {}
    },
    {
      "id": "/page/0/Text/22",
      "block_type": "Text",
      "html": "<p block-type=\"Text\">NV BOCO, 9000 Gent, Maisstraat 62</p>",
      "page": 187,
      "polygon": [
        [
          71.0078125,
          355.6524353027344
        ],
        [
          221.9150390625,
          355.6524353027344
        ],
        [
          221.9150390625,
          365.4024353027344
        ],
        [
          71.0078125,
          365.4024353027344
        ]
      ],
      "bbox": [
        71.0078125,
        355.6524353027344,
        221.9150390625,
        365.4024353027344
      ],
      "section_hierarchy": {
        "1": "/page/0/SectionHeader/0",
        "4": "/page/0/SectionHeader/1"
      },
      "images": {}
    },
    {
      "id": "/page/0/Text/23",
      "block_type": "Text",
      "html": "<p block-type=\"Text\">en</p>",
      "page": 187,
      "polygon": [
        [
          70.42578125,
          367.6524353027344
        ],
        [
          81.47699737548828,
          367.6524353027344
        ],
        [
          81.47699737548828,
          377.4024353027344
        ],
        [
          70.42578125,
          377.4024353027344
        ]
      ],
      "bbox": [
        70.42578125,
        367.6524353027344,
        81.47699737548828,
        377.4024353027344
      ],
      "section_hierarchy": {
        "1": "/page/0/SectionHeader/0",
        "4": "/page/0/SectionHeader/1"
      },
      "images": {}
    },
    {
      "id": "/page/0/Text/24",
      "block_type": "Text",
      "html": "<p block-type=\"Text\">BVBA MAZ, 9060 Zelzate, Suikerkaai 17</p>",
      "page": 187,
      "polygon": [
        [
          70.42578125,
          378.9024353027344
        ],
        [
          241.54296875000003,
          378.9024353027344
        ],
        [
          241.54296875000003,
          388.6524353027344
        ],
        [
          70.42578125,
          388.6524353027344
        ]
      ],
      "bbox": [
        70.42578125,
        378.9024353027344,
        241.54296875000003,
        388.6524353027344
      ],
      "section_hierarchy": {
        "1": "/page/0/SectionHeader/0",
        "4": "/page/0/SectionHeader/1"
      },
      "images": {}
    },
    {
      "id": "/page/0/Text/25",
      "block_type": "Text",
      "html": "<p block-type=\"Text\">en</p>",
      "page": 187,
      "polygon": [
        [
          71.298828125,
          390.1524353027344
        ],
        [
          81.47699737548828,
          390.1524353027344
        ],
        [
          81.47699737548828,
          400.0322265625
        ],
        [
          71.298828125,
          400.0322265625
        ]
      ],
      "bbox": [
        71.298828125,
        390.1524353027344,
        81.47699737548828,
        400.0322265625
      ],
      "section_hierarchy": {
        "1": "/page/0/SectionHeader/0",
        "4": "/page/0/SectionHeader/1"
      },
      "images": {}
    },
    {
      "id": "/page/0/Text/26",
      "block_type": "Text",
      "html": "<p block-type=\"Text\">BVBA MAG, 9000 Gent, Maisstraat 62</p>",
      "page": 187,
      "polygon": [
        [
          71.0078125,
          402.1524353027344
        ],
        [
          231.64843750000003,
          402.1524353027344
        ],
        [
          231.64843750000003,
          414.0107421875
        ],
        [
          71.0078125,
          414.0107421875
        ]
      ],
      "bbox": [
        71.0078125,
        402.1524353027344,
        231.64843750000003,
        414.0107421875
      ],
      "section_hierarchy": {
        "1": "/page/0/SectionHeader/0",
        "4": "/page/0/SectionHeader/1"
      },
      "images": {}
    },
    {
      "id": "/page/0/Text/27",
      "block_type": "Text",
      "html": "<p block-type=\"Text\">en</p>",
      "page": 187,
      "polygon": [
        [
          71.298828125,
          413.4024353027344
        ],
        [
          81.47699737548828,
          413.4024353027344
        ],
        [
          81.47699737548828,
          425.111328125
        ],
        [
          71.298828125,
          425.111328125
        ]
      ],
      "bbox": [
        71.298828125,
        413.4024353027344,
        81.47699737548828,
        425.111328125
      ],
      "section_hierarchy": {
        "1": "/page/0/SectionHeader/0",
        "4": "/page/0/SectionHeader/1"
      },
      "images": {}
    },
    {
      "id": "/page/0/Text/28",
      "block_type": "Text",
      "html": "<p block-type=\"Text\">MAATSCHAP BOUWMARKT GENT, 9000 Gent, Maisstraat 62</p>",
      "page": 187,
      "polygon": [
        [
          69.26171875,
          424.6524353027344
        ],
        [
          337.40631103515625,
          424.6524353027344
        ],
        [
          337.40631103515625,
          438.6787109375
        ],
        [
          69.26171875,
          438.6787109375
        ]
      ],
      "bbox": [
        69.26171875,
        424.6524353027344,
        337.40631103515625,
        438.6787109375
      ],
      "section_hierarchy": {
        "1": "/page/0/SectionHeader/0",
        "4": "/page/0/SectionHeader/1"
      },
      "images": {}
    },
    {
      "id": "/page/0/Text/29",
      "block_type": "Text",
      "html": "<p block-type=\"Text\">en</p>",
      "page": 187,
      "polygon": [
        [
          71.0078125,
          436.6524353027344
        ],
        [
          81.484375,
          436.6524353027344
        ],
        [
          81.484375,
          448.5458984375
        ],
        [
          71.0078125,
          448.5458984375
        ]
      ],
      "bbox": [
        71.0078125,
        436.6524353027344,
        81.484375,
        448.5458984375
      ],
      "section_hierarchy": {
        "1": "/page/0/SectionHeader/0",
        "4": "/page/0/SectionHeader/1"
      },
      "images": {}
    },
    {
      "id": "/page/0/Text/30",
      "block_type": "Text",
      "html": "<p block-type=\"Text\">BVBA ANDENNE BRICOLAGE, 9000 Gent, Maisstraat 62</p>",
      "page": 187,
      "polygon": [
        [
          71.0078125,
          447.9024353027344
        ],
        [
          317.7890625,
          447.9024353027344
        ],
        [
          317.7890625,
          461.7021484375
        ],
        [
          71.0078125,
          461.7021484375
        ]
      ],
      "bbox": [
        71.0078125,
        447.9024353027344,
        317.7890625,
        461.7021484375
      ],
      "section_hierarchy": {
        "1": "/page/0/SectionHeader/0",
        "4": "/page/0/SectionHeader/1"
      },
      "images": {}
    },
    {
      "id": "/page/0/Text/31",
      "block_type": "Text",
      "html": "<p block-type=\"Text\">en</p>",
      "page": 187,
      "polygon": [
        [
          71.58984375,
          459.1524353027344
        ],
        [
          82.06640625,
          459.1524353027344
        ],
        [
          82.06640625,
          471.5693359375
        ],
        [
          71.58984375,
          471.5693359375
        ]
      ],
      "bbox": [
        71.58984375,
        459.1524353027344,
        82.06640625,
        471.5693359375
      ],
      "section_hierarchy": {
        "1": "/page/0/SectionHeader/0",
        "4": "/page/0/SectionHeader/1"
      },
      "images": {}
    },
    {
      "id": "/page/0/Text/32",
      "block_type": "Text",
      "html": "<p block-type=\"Text\">BVBA BRAINE L'ALLEUD BRICOLAGE, 9000 Gent, Maisstraat 62</p>",
      "page": 187,
      "polygon": [
        [
          71.0078125,
          471.1524353027344
        ],
        [
          356.89453125,
          471.1524353027344
        ],
        [
          356.89453125,
          481.4365234375
        ],
        [
          71.0078125,
          481.4365234375
        ]
      ],
      "bbox": [
        71.0078125,
        471.1524353027344,
        356.89453125,
        481.4365234375
      ],
      "section_hierarchy": {
        "1": "/page/0/SectionHeader/0",
        "4": "/page/0/SectionHeader/1"
      },
      "images": {}
    },
    {
      "id": "/page/0/Text/33",
      "block_type": "Text",
      "html": "<p block-type=\"Text\">en</p>",
      "page": 187,
      "polygon": [
        [
          70.716796875,
          482.2587890625
        ],
        [
          81.775390625,
          482.2587890625
        ],
        [
          81.775390625,
          492.1524353027344
        ],
        [
          70.716796875,
          492.1524353027344
        ]
      ],
      "bbox": [
        70.716796875,
        482.2587890625,
        81.775390625,
        492.1524353027344
      ],
      "section_hierarchy": {
        "1": "/page/0/SectionHeader/0",
        "4": "/page/0/SectionHeader/1"
      },
      "images": {}
    },
    {
      "id": "/page/0/Text/34",
      "block_type": "Text",
      "html": "<p block-type=\"Text\">BVBA LOKEREN DOE HET ZELF, 9000 Gent, Maisstraat 62</p>",
      "page": 187,
      "polygon": [
        [
          71.58984375,
          493.6524353027344
        ],
        [
          326.51953125,
          493.6524353027344
        ],
        [
          326.51953125,
          504.4599609375
        ],
        [
          71.58984375,
          504.4599609375
        ]
      ],
      "bbox": [
        71.58984375,
        493.6524353027344,
        326.51953125,
        504.4599609375
      ],
      "section_hierarchy": {
        "1": "/page/0/SectionHeader/0",
        "4": "/page/0/SectionHeader/1"
      },
      "images": {}
    },
    {
      "id": "/page/0/Text/35",
      "block_type": "Text",
      "html": "<p block-type=\"Text\">Gelet op de Wet op de Bescherming van de Economische Mededinging, zoals gecoördineerd op 1 juli  1999 (WBEM) ;</p>",
      "page": 187,
      "polygon": [
        [
          71.0078125,
          510.44512939453125
        ],
        [
          528.41748046875,
          510.44512939453125
        ],
        [
          528.41748046875,
          534.47265625
        ],
        [
          71.0078125,
          534.47265625
        ]
      ],
      "bbox": [
        71.0078125,
        510.44512939453125,
        528.41748046875,
        534.47265625
      ],
      "section_hierarchy": {
        "1": "/page/0/SectionHeader/0",
        "4": "/page/0/SectionHeader/1"
      },
      "images": {}
    },
    {
      "id": "/page/0/Text/36",
      "block_type": "Text",
      "html": "<p block-type=\"Text\">Gezien de aanmelding aan het Secretariaat van de Raad voor de Mededinging van een con-centratie,  neergelegd op 19 november 2001 ;</p>",
      "page": 187,
      "polygon": [
        [
          71.0078125,
          547.1951293945312
        ],
        [
          528.561279296875,
          547.1951293945312
        ],
        [
          528.561279296875,
          571.1951293945312
        ],
        [
          71.0078125,
          571.1951293945312
        ]
      ],
      "bbox": [
        71.0078125,
        547.1951293945312,
        528.561279296875,
        571.1951293945312
      ],
      "section_hierarchy": {
        "1": "/page/0/SectionHeader/0",
        "4": "/page/0/SectionHeader/1"
      },
      "images": {}
    },
    {
      "id": "/page/0/Text/37",
      "block_type": "Text",
      "html": "<p block-type=\"Text\">Gezien de mededeling voor onderzoek door het Secretariaat van de Raad aan het korps van verslaggevers conform art.32bis §1 WBEM op 22 november 2001 ;</p>",
      "page": 187,
      "polygon": [
        [
          71.0078125,
          584.6951293945312
        ],
        [
          525.8978271484375,
          584.6951293945312
        ],
        [
          525.8978271484375,
          610.12109375
        ],
        [
          71.0078125,
          610.12109375
        ]
      ],
      "bbox": [
        71.0078125,
        584.6951293945312,
        525.8978271484375,
        610.12109375
      ],
      "section_hierarchy": {
        "1": "/page/0/SectionHeader/0",
        "4": "/page/0/SectionHeader/1"
      },
      "images": {}
    },
    {
      "id": "/page/0/Text/38",
      "block_type": "Text",
      "html": "<p block-type=\"Text\">Gezien de stukken van het dossier en het gemotiveerde verslag van de Dienst voor de Mede-dinging  zoals medegedeeld aan de verslaggever op 16 januari 2002 ;</p>",
      "page": 187,
      "polygon": [
        [
          71.0078125,
          622.1951293945312
        ],
        [
          528.5628662109375,
          622.1951293945312
        ],
        [
          528.5628662109375,
          646.30078125
        ],
        [
          71.0078125,
          646.30078125
        ]
      ],
      "bbox": [
        71.0078125,
        622.1951293945312,
        528.5628662109375,
        646.30078125
      ],
      "section_hierarchy": {
        "1": "/page/0/SectionHeader/0",
        "4": "/page/0/SectionHeader/1"
      },
      "images": {}
    },
    {
      "id": "/page/0/Text/39",
      "block_type": "Text",
      "html": "<p block-type=\"Text\">Gezien het gemotiveerd verslag van de verslaggever zoals dit op 17 januari 2002 werd opge-steld en  op 18 januari 2002 werd betekend aan de Raad ;</p>",
      "page": 187,
      "polygon": [
        [
          69.84375,
          659.45703125
        ],
        [
          527.8124389648438,
          659.45703125
        ],
        [
          527.8124389648438,
          683.6951293945312
        ],
        [
          69.84375,
          683.6951293945312
        ]
      ],
      "bbox": [
        69.84375,
        659.45703125,
        527.8124389648438,
        683.6951293945312
      ],
      "section_hierarchy": {
        "1": "/page/0/SectionHeader/0",
        "4": "/page/0/SectionHeader/1"
      },
      "images": {}
    },
    {
      "id": "/page/0/Text/40",
      "block_type": "Text",
      "html": "<p block-type=\"Text\">Gehoord het verslag van de verslaggever dhr. Bert Stulens ;</p>",
      "page": 187,
      "polygon": [
        [
          70.42578125,
          696.0478515625
        ],
        [
          334.66796875,
          696.0478515625
        ],
        [
          334.66796875,
          707.6951293945312
        ],
        [
          70.42578125,
          707.6951293945312
        ]
      ],
      "bbox": [
        70.42578125,
        696.0478515625,
        334.66796875,
        707.6951293945312
      ],
      "section_hierarchy": {
        "1": "/page/0/SectionHeader/0",
        "4": "/page/0/SectionHeader/1"
      },
      "images": {}
    },
    {
      "id": "/page/0/Text/41",
      "block_type": "Text",
      "html": "<p block-type=\"Text\">Gehoord de partijen die verschenen ter zitting op 8 februari 2002:</p>",
      "page": 187,
      "polygon": [
        [
          71.0078125,
          721.1951217651367
        ],
        [
          361.6416931152344,
          721.1951217651367
        ],
        [
          361.6416931152344,
          732.4451217651367
        ],
        [
          71.0078125,
          732.4451217651367
        ]
      ],
      "bbox": [
        71.0078125,
        721.1951217651367,
        361.6416931152344,
        732.4451217651367
      ],
      "section_hierarchy": {
        "1": "/page/0/SectionHeader/0",
        "4": "/page/0/SectionHeader/1"
      },
      "images": {}
    },
    {
      "id": "/page/0/Text/42",
      "block_type": "Text",
      "html": "<p block-type=\"Text\">- mr. Coox.</p>",
      "page": 187,
      "polygon": [
        [
          71.298828125,
          738.8056640625
        ],
        [
          129.76058959960938,
          738.8056640625
        ],
        [
          129.76058959960938,
          750.9024353027344
        ],
        [
          71.298828125,
          750.9024353027344
        ]
      ],
      "bbox": [
        71.298828125,
        738.8056640625,
        129.76058959960938,
        750.9024353027344
      ],
      "section_hierarchy": {
        "1": "/page/0/SectionHeader/0",
        "4": "/page/0/SectionHeader/1"
      },
      "images": {}
    },
    {
      "id": "/page/1/SectionHeader/0",
      "block_type": "SectionHeader",
      "html": "<h4>1. De aanmeldende en betrokken partijen</h4>",
      "page": 142,
      "polygon": [
        [
          72.0,
          73.27752685546875
        ],
        [
          296.16827392578125,
          73.27752685546875
        ],
        [
          296.16827392578125,
          85.27752685546875
        ],
        [
          72.0,
          85.27752685546875
        ]
      ],
      "bbox": [
        72.0,
        73.27752685546875,
        296.16827392578125,
        85.27752685546875
      ],
      "section_hierarchy": {
        "1": "/page/0/SectionHeader/0",
        "4": "/page/1/SectionHeader/0"
      },
      "images": {}
    },
    {
      "id": "/page/1/ListGroup/142",
      "block_type": "ListGroup",
      "html": "<p block-type=\"ListGroup\"><ul><li block-type=\"ListItem\"> Als koper treedt op: NV BRICORAMA, een 100% dochteronderneming van SA BRICO-RAMA FRANCE,  Boulevard du Maréchal de Lattre de Tassiny 21, Fontenay sous Bois, Frankrijk. Het zijn vestigingen met een aanzienlijke opslag- en verkoopsruimte voor doe-het-zelf materiaal.</li><li block-type=\"ListItem\"> Als verkopers treden op: NV POGAM, NV TERBASSENWEI, NV C.B. BOUWMARK-TEN en Mr.  POLLET &amp; Mrs. WYTINCK.</li><li block-type=\"ListItem\"> Doelondernemingen met directe controleverwerving: NV BOUWMAR, NV ROBO, NV WABO, NV  MULTI HOBBY, NV C.B. BOUWMARKTEN, BVBA GRUTO en NV BOCO.</li><li block-type=\"ListItem\"> Er is indirecte controleverwerving (via overname van NV C.B. BOUWMARKTEN) van: BVBA MAZ,  BVBA MAG, MAATSCHAP BOUWMARKT GENT, BVBA ANDENNE BRICOLAGE, BVBA BRAINE  L'ALLEUD BRICOLAGE en BVBA LOKEREN DOE HET ZELF.</li></ul></p>",
      "page": 142,
      "polygon": [
        [
          69.84375,
          88.8046875
        ],
        [
          528.5631103515625,
          88.8046875
        ],
        [
          528.5631103515625,
          211.6524658203125
        ],
        [
          69.84375,
          211.6524658203125
        ]
      ],
      "bbox": [
        69.84375,
        88.8046875,
        528.5631103515625,
        211.6524658203125
      ],
      "section_hierarchy": {
        "1": "/page/0/SectionHeader/0",
        "4": "/page/1/SectionHeader/0"
      },
      "images": {}
    },
    {
      "id": "/page/1/Text/5",
      "block_type": "Text",
      "html": "<p block-type=\"Text\">Genoemde vennootschappen zijn alle ondernemingen in de zin van art. 1 WBEM.</p>",
      "page": 142,
      "polygon": [
        [
          69.84375,
          220.94512939453125
        ],
        [
          431.50872802734375,
          220.94512939453125
        ],
        [
          431.50872802734375,
          232.19512939453125
        ],
        [
          69.84375,
          232.19512939453125
        ]
      ],
      "bbox": [
        69.84375,
        220.94512939453125,
        431.50872802734375,
        232.19512939453125
      ],
      "section_hierarchy": {
        "1": "/page/0/SectionHeader/0",
        "4": "/page/1/SectionHeader/0"
      },
      "images": {}
    },
    {
      "id": "/page/1/SectionHeader/6",
      "block_type": "SectionHeader",
      "html": "<h2>2. Aanmeldingsplicht – overeenkomst van concentratie</h2>",
      "page": 142,
      "polygon": [
        [
          71.0078125,
          253.27752685546875
        ],
        [
          365.9840087890625,
          253.27752685546875
        ],
        [
          365.9840087890625,
          265.591796875
        ],
        [
          71.0078125,
          265.591796875
        ]
      ],
      "bbox": [
        71.0078125,
        253.27752685546875,
        365.9840087890625,
        265.591796875
      ],
      "section_hierarchy": {
        "1": "/page/0/SectionHeader/0",
        "2": "/page/1/SectionHeader/6"
      },
      "images": {}
    },
    {
      "id": "/page/1/Text/7",
      "block_type": "Text",
      "html": "<p block-type=\"Text\">De concentratie betreft de overname via aankoop van de aandelen van een reeks ondernemin-gen, alle  actief in de doe-het-zelf sector, die rechtstreeks of onrechtstreeks worden bestuurd door dhr. Pollet.  De NV BRICORAMA verwerft een directe of indirecte controle over de overgenomen ondernemingen. Deze laatste hebben ook een franciseovereenkomst met het merk \"GAMMA\".</p>",
      "page": 142,
      "polygon": [
        [
          71.0078125,
          274.94512939453125
        ],
        [
          528.937255859375,
          274.94512939453125
        ],
        [
          528.937255859375,
          323.69512939453125
        ],
        [
          71.0078125,
          323.69512939453125
        ]
      ],
      "bbox": [
        71.0078125,
        274.94512939453125,
        528.937255859375,
        323.69512939453125
      ],
      "section_hierarchy": {
        "1": "/page/0/SectionHeader/0",
        "2": "/page/1/SectionHeader/6"
      },
      "images": {}
    },
    {
      "id": "/page/1/Text/8",
      "block_type": "Text",
      "html": "<p block-type=\"Text\">Deze operatie is een concentratie in de zin van art. 9 §1a WBEM.</p>",
      "page": 142,
      "polygon": [
        [
          71.0078125,
          336.7177734375
        ],
        [
          360.91192626953125,
          336.7177734375
        ],
        [
          360.91192626953125,
          348.44512939453125
        ],
        [
          71.0078125,
          348.44512939453125
        ]
      ],
      "bbox": [
        71.0078125,
        336.7177734375,
        360.91192626953125,
        348.44512939453125
      ],
      "section_hierarchy": {
        "1": "/page/0/SectionHeader/0",
        "2": "/page/1/SectionHeader/6"
      },
      "images": {}
    },
    {
      "id": "/page/1/Text/9",
      "block_type": "Text",
      "html": "<p block-type=\"Text\">De overeenkomst werd ondertekend op 18 oktober 2001.</p>",
      "page": 142,
      "polygon": [
        [
          71.58984375,
          361.94512939453125
        ],
        [
          321.2056884765625,
          361.94512939453125
        ],
        [
          321.2056884765625,
          373.7197265625
        ],
        [
          71.58984375,
          373.7197265625
        ]
      ],
      "bbox": [
        71.58984375,
        361.94512939453125,
        321.2056884765625,
        373.7197265625
      ],
      "section_hierarchy": {
        "1": "/page/0/SectionHeader/0",
        "2": "/page/1/SectionHeader/6"
      },
      "images": {}
    },
    {
      "id": "/page/1/Text/10",
      "block_type": "Text",
      "html": "<p block-type=\"Text\">De concentratie werd tijdig aangemeld op 19 november 2001. De ontbrekende inlichtingen werden  binnen de door de verslaggever aan de partijen toegekende termijn verstrekt.</p>",
      "page": 142,
      "polygon": [
        [
          71.0078125,
          386.46484375
        ],
        [
          527.1168212890625,
          386.46484375
        ],
        [
          527.1168212890625,
          410.69512939453125
        ],
        [
          71.0078125,
          410.69512939453125
        ]
      ],
      "bbox": [
        71.0078125,
        386.46484375,
        527.1168212890625,
        410.69512939453125
      ],
      "section_hierarchy": {
        "1": "/page/0/SectionHeader/0",
        "2": "/page/1/SectionHeader/6"
      },
      "images": {}
    },
    {
      "id": "/page/1/Text/11",
      "block_type": "Text",
      "html": "<p block-type=\"Text\">Uit de voorgelegde (vertrouwelijke) omzetcijfers van de betrokken ondernemingen blijkt dat de  drempels zoals opgelegd conform art. 11 §1 WBEM worden behaald, zodat de concentratie diende te  worden aangemeld.</p>",
      "page": 142,
      "polygon": [
        [
          71.0078125,
          423.0556640625
        ],
        [
          527.2122802734375,
          423.0556640625
        ],
        [
          527.2122802734375,
          460.19512939453125
        ],
        [
          71.0078125,
          460.19512939453125
        ]
      ],
      "bbox": [
        71.0078125,
        423.0556640625,
        527.2122802734375,
        460.19512939453125
      ],
      "section_hierarchy": {
        "1": "/page/0/SectionHeader/0",
        "2": "/page/1/SectionHeader/6"
      },
      "images": {}
    },
    {
      "id": "/page/1/Text/12",
      "block_type": "Text",
      "html": "<p block-type=\"Text\">De aangemelde concentratie valt overeenkomstig art. 33 §1.1 WBEM binnen het toepassingsgebied  van de wet.</p>",
      "page": 142,
      "polygon": [
        [
          71.0078125,
          473.2138671875
        ],
        [
          528.5655517578125,
          473.2138671875
        ],
        [
          528.5655517578125,
          497.69512939453125
        ],
        [
          71.0078125,
          497.69512939453125
        ]
      ],
      "bbox": [
        71.0078125,
        473.2138671875,
        528.5655517578125,
        497.69512939453125
      ],
      "section_hierarchy": {
        "1": "/page/0/SectionHeader/0",
        "2": "/page/1/SectionHeader/6"
      },
      "images": {}
    },
    {
      "id": "/page/1/SectionHeader/13",
      "block_type": "SectionHeader",
      "html": "<h2>3. De relevante productenmarkten</h2>",
      "page": 142,
      "polygon": [
        [
          71.0078125,
          518.4384765625
        ],
        [
          256.4635925292969,
          518.4384765625
        ],
        [
          256.4635925292969,
          530.7775268554688
        ],
        [
          71.0078125,
          530.7775268554688
        ]
      ],
      "bbox": [
        71.0078125,
        518.4384765625,
        256.4635925292969,
        530.7775268554688
      ],
      "section_hierarchy": {
        "1": "/page/0/SectionHeader/0",
        "2": "/page/1/SectionHeader/13"
      },
      "images": {}
    },
    {
      "id": "/page/1/Text/14",
      "block_type": "Text",
      "html": "<p block-type=\"Text\">Het betreft de markt van de kleinhandel in doe-het-zelf producten bestaande uit grote ketens en  zelfstandigen die verkopen aan het grote publiek, zowel particulieren en professionelen.</p>",
      "page": 142,
      "polygon": [
        [
          71.0078125,
          539.6951293945312
        ],
        [
          525.9933471679688,
          539.6951293945312
        ],
        [
          525.9933471679688,
          564.07421875
        ],
        [
          71.0078125,
          564.07421875
        ]
      ],
      "bbox": [
        71.0078125,
        539.6951293945312,
        525.9933471679688,
        564.07421875
      ],
      "section_hierarchy": {
        "1": "/page/0/SectionHeader/0",
        "2": "/page/1/SectionHeader/13"
      },
      "images": {}
    },
    {
      "id": "/page/1/SectionHeader/15",
      "block_type": "SectionHeader",
      "html": "<h1>4. De relevante geografische markt</h1>",
      "page": 142,
      "polygon": [
        [
          71.0078125,
          584.2197265625
        ],
        [
          262.4200134277344,
          584.2197265625
        ],
        [
          262.4200134277344,
          596.7775268554688
        ],
        [
          71.0078125,
          596.7775268554688
        ]
      ],
      "bbox": [
        71.0078125,
        584.2197265625,
        262.4200134277344,
        596.7775268554688
      ],
      "section_hierarchy": {
        "1": "/page/1/SectionHeader/15"
      },
      "images": {}
    },
    {
      "id": "/page/1/Text/16",
      "block_type": "Text",
      "html": "<p block-type=\"Text\">De relevante geografische markt is België.</p>",
      "page": 142,
      "polygon": [
        [
          72.0,
          605.6951293945312
        ],
        [
          259.64215087890625,
          605.6951293945312
        ],
        [
          259.64215087890625,
          616.9451293945312
        ],
        [
          72.0,
          616.9451293945312
        ]
      ],
      "bbox": [
        72.0,
        605.6951293945312,
        259.64215087890625,
        616.9451293945312
      ],
      "section_hierarchy": {
        "1": "/page/1/SectionHeader/15"
      },
      "images": {}
    },
    {
      "id": "/page/1/SectionHeader/17",
      "block_type": "SectionHeader",
      "html": "<h1>5. De marktaandelen</h1>",
      "page": 142,
      "polygon": [
        [
          71.0078125,
          636.8447265625
        ],
        [
          187.39520263671875,
          636.8447265625
        ],
        [
          187.39520263671875,
          650.0275268554688
        ],
        [
          71.0078125,
          650.0275268554688
        ]
      ],
      "bbox": [
        71.0078125,
        636.8447265625,
        187.39520263671875,
        650.0275268554688
      ],
      "section_hierarchy": {
        "1": "/page/1/SectionHeader/17"
      },
      "images": {}
    },
    {
      "id": "/page/1/Text/18",
      "block_type": "Text",
      "html": "<p block-type=\"Text\">Op de markt voor de kleinhandel van doe-het-zelf zaken voor het grote publiek in België, bedraagt het  gezamenlijk marktaandeel na de betrokken concentratie minder dan 5%. Wanneer de markt in de enge  zin wordt beschouwd (uitsluitend de ketens), beloopt dit gezamenlijk marktaandeel minder dan 15%.</p>",
      "page": 142,
      "polygon": [
        [
          71.0078125,
          659.6951293945312
        ],
        [
          528.5626831054688,
          659.6951293945312
        ],
        [
          528.5626831054688,
          695.6951293945312
        ],
        [
          71.0078125,
          695.6951293945312
        ]
      ],
      "bbox": [
        71.0078125,
        659.6951293945312,
        528.5626831054688,
        695.6951293945312
      ],
      "section_hierarchy": {
        "1": "/page/1/SectionHeader/17"
      },
      "images": {}
    },
    {
      "id": "/page/1/SectionHeader/19",
      "block_type": "SectionHeader",
      "html": "<h4>6. Economische analyse</h4>",
      "page": 142,
      "polygon": [
        [
          70.716796875,
          716.7775268554688
        ],
        [
          204.73171997070312,
          716.7775268554688
        ],
        [
          204.73171997070312,
          728.7775268554688
        ],
        [
          70.716796875,
          728.7775268554688
        ]
      ],
      "bbox": [
        70.716796875,
        716.7775268554688,
        204.73171997070312,
        728.7775268554688
      ],
      "section_hierarchy": {
        "1": "/page/1/SectionHeader/17",
        "4": "/page/1/SectionHeader/19"
      },
      "images": {}
    },
    {
      "id": "/page/1/Text/20",
      "block_type": "Text",
      "html": "<p block-type=\"Text\">Uit het onderzoek van de Dienst voor de Mededinging blijkt dat de aanmelders, de concurrenten en de  leveranciers allen stellen dat binnen de doe-het-zelf sector, zowel de grote ketens (met grote</p>",
      "page": 142,
      "polygon": [
        [
          71.0078125,
          738.4451217651367
        ],
        [
          528.56494140625,
          738.4451217651367
        ],
        [
          528.56494140625,
          761.6951217651367
        ],
        [
          71.0078125,
          761.6951217651367
        ]
      ],
      "bbox": [
        71.0078125,
        738.4451217651367,
        528.56494140625,
        761.6951217651367
      ],
      "section_hierarchy": {
        "1": "/page/1/SectionHeader/17",
        "4": "/page/1/SectionHeader/19"
      },
      "images": {}
    },
    {
      "id": "/page/2/Text/0",
      "block_type": "Text",
      "html": "<p block-type=\"Text\">opslagruimte en verkoopoppervlakte) als de zelfstandigen tot dezelfde markt behoren. Gezien de  onderzochte marktaandelen, is de verschuiving na de fusie dan ook zeer gering op de totale markt van  de doe-het-zelf sector.</p>",
      "page": 81,
      "polygon": [
        [
          71.0078125,
          71.537109375
        ],
        [
          528.562255859375,
          71.537109375
        ],
        [
          528.562255859375,
          107.69512939453125
        ],
        [
          71.0078125,
          107.69512939453125
        ]
      ],
      "bbox": [
        71.0078125,
        71.537109375,
        528.562255859375,
        107.69512939453125
      ],
      "section_hierarchy": {
        "1": "/page/1/SectionHeader/17",
        "4": "/page/1/SectionHeader/19"
      },
      "images": {}
    },
    {
      "id": "/page/2/Text/1",
      "block_type": "Text",
      "html": "<p block-type=\"Text\">Door de concentratie worden in België alle BRICORAMA-vestigingen GAMMA-winkels. Het  marktaandeel van GAMMA wordt zodoende geconsolideerd. De positie van GAMMA is en blijft op  de tweede plaats na marktleider BRICO en dus treedt er geen verschuiving op.</p>",
      "page": 81,
      "polygon": [
        [
          71.0078125,
          121.19512939453125
        ],
        [
          528.3606567382812,
          121.19512939453125
        ],
        [
          528.3606567382812,
          157.94512939453125
        ],
        [
          71.0078125,
          157.94512939453125
        ]
      ],
      "bbox": [
        71.0078125,
        121.19512939453125,
        528.3606567382812,
        157.94512939453125
      ],
      "section_hierarchy": {
        "1": "/page/1/SectionHeader/17",
        "4": "/page/1/SectionHeader/19"
      },
      "images": {}
    },
    {
      "id": "/page/2/Text/2",
      "block_type": "Text",
      "html": "<p block-type=\"Text\">BRICORAMA wordt een belangrijke franchisehouder binnen de GAMMA-groep. De concurrentie  wordt echter niet belemmerd, omdat de markt van de kleinhandel van de doe-het-zelf sector zeer  versnipperd is in België.</p>",
      "page": 81,
      "polygon": [
        [
          72.0,
          171.44512939453125
        ],
        [
          527.8123168945312,
          171.44512939453125
        ],
        [
          527.8123168945312,
          207.6220703125
        ],
        [
          72.0,
          207.6220703125
        ]
      ],
      "bbox": [
        72.0,
        171.44512939453125,
        527.8123168945312,
        207.6220703125
      ],
      "section_hierarchy": {
        "1": "/page/1/SectionHeader/17",
        "4": "/page/1/SectionHeader/19"
      },
      "images": {}
    },
    {
      "id": "/page/2/Text/3",
      "block_type": "Text",
      "html": "<p block-type=\"Text\">Gezien er enorm veel spelers zijn op deze markt, is het duidelijk dat huidige concentratie geen machtspositie in het leven roept of versterkt, die tot gevolg heeft dat de daadwerkelijke mededinging  op significante wijze wordt belemmerd (art. 10 §3 WBEM).</p>",
      "page": 81,
      "polygon": [
        [
          71.0078125,
          220.94512939453125
        ],
        [
          527.864990234375,
          220.94512939453125
        ],
        [
          527.864990234375,
          257.7802734375
        ],
        [
          71.0078125,
          257.7802734375
        ]
      ],
      "bbox": [
        71.0078125,
        220.94512939453125,
        527.864990234375,
        257.7802734375
      ],
      "section_hierarchy": {
        "1": "/page/1/SectionHeader/17",
        "4": "/page/1/SectionHeader/19"
      },
      "images": {}
    },
    {
      "id": "/page/2/Text/4",
      "block_type": "Text",
      "html": "<p block-type=\"Text\">De Raad beslist dan ook dat de voorgelegde concentratie kan worden toegelaten conform art. 33 §2.1.a  WBEM.</p>",
      "page": 81,
      "polygon": [
        [
          71.0078125,
          270.9365234375
        ],
        [
          527.903564453125,
          270.9365234375
        ],
        [
          527.903564453125,
          295.19512939453125
        ],
        [
          71.0078125,
          295.19512939453125
        ]
      ],
      "bbox": [
        71.0078125,
        270.9365234375,
        527.903564453125,
        295.19512939453125
      ],
      "section_hierarchy": {
        "1": "/page/1/SectionHeader/17",
        "4": "/page/1/SectionHeader/19"
      },
      "images": {}
    },
    {
      "id": "/page/2/SectionHeader/5",
      "block_type": "SectionHeader",
      "html": "<h4>OM DEZE REDENEN</h4>",
      "page": 81,
      "polygon": [
        [
          70.42578125,
          316.1611328125
        ],
        [
          191.3355712890625,
          316.1611328125
        ],
        [
          191.3355712890625,
          328.27752685546875
        ],
        [
          70.42578125,
          328.27752685546875
        ]
      ],
      "bbox": [
        70.42578125,
        316.1611328125,
        191.3355712890625,
        328.27752685546875
      ],
      "section_hierarchy": {
        "1": "/page/1/SectionHeader/17",
        "4": "/page/2/SectionHeader/5"
      },
      "images": {}
    },
    {
      "id": "/page/2/SectionHeader/6",
      "block_type": "SectionHeader",
      "html": "<h1>DE RAAD VOOR DE MEDEDINGING</h1>",
      "page": 81,
      "polygon": [
        [
          72.0,
          344.1181640625
        ],
        [
          273.67474365234375,
          344.1181640625
        ],
        [
          273.67474365234375,
          356.77752685546875
        ],
        [
          72.0,
          356.77752685546875
        ]
      ],
      "bbox": [
        72.0,
        344.1181640625,
        273.67474365234375,
        356.77752685546875
      ],
      "section_hierarchy": {
        "1": "/page/2/SectionHeader/6"
      },
      "images": {}
    },
    {
      "id": "/page/2/Text/7",
      "block_type": "Text",
      "html": "<p block-type=\"Text\">Gelet op de art. 2 e.v. van de Wet van 15 juni 1935 op het taalgebruik in gerechtszaken van toepassing  overeenkomstig art. 54bis WBEM ;</p>",
      "page": 81,
      "polygon": [
        [
          71.0078125,
          365.0859375
        ],
        [
          528.5628051757812,
          365.0859375
        ],
        [
          528.5628051757812,
          389.69512939453125
        ],
        [
          71.0078125,
          389.69512939453125
        ]
      ],
      "bbox": [
        71.0078125,
        365.0859375,
        528.5628051757812,
        389.69512939453125
      ],
      "section_hierarchy": {
        "1": "/page/2/SectionHeader/6"
      },
      "images": {}
    },
    {
      "id": "/page/2/Text/8",
      "block_type": "Text",
      "html": "<p block-type=\"Text\">Stelt vast dat de betrokken concentratie aanmeldingsplichtig is en conform art. 33 § 1.1 WBEM binnen het toepassingsgebied valt van de wet ;</p>",
      "page": 81,
      "polygon": [
        [
          71.0078125,
          402.4990234375
        ],
        [
          525.8931884765625,
          402.4990234375
        ],
        [
          525.8931884765625,
          427.19512939453125
        ],
        [
          71.0078125,
          427.19512939453125
        ]
      ],
      "bbox": [
        71.0078125,
        402.4990234375,
        525.8931884765625,
        427.19512939453125
      ],
      "section_hierarchy": {
        "1": "/page/2/SectionHeader/6"
      },
      "images": {}
    },
    {
      "id": "/page/2/Text/9",
      "block_type": "Text",
      "html": "<p block-type=\"Text\">Verklaart de concentratie toelaatbaar conform art. 33 §2.1.a WBEM ;</p>",
      "page": 81,
      "polygon": [
        [
          71.0078125,
          440.69512939453125
        ],
        [
          378.1130676269531,
          440.69512939453125
        ],
        [
          378.1130676269531,
          451.94512939453125
        ],
        [
          71.0078125,
          451.94512939453125
        ]
      ],
      "bbox": [
        71.0078125,
        440.69512939453125,
        378.1130676269531,
        451.94512939453125
      ],
      "section_hierarchy": {
        "1": "/page/2/SectionHeader/6"
      },
      "images": {}
    },
    {
      "id": "/page/2/Text/10",
      "block_type": "Text",
      "html": "<p block-type=\"Text\">Aldus uitgesproken op 8 februari 2002 door de Kamer van de Raad voor de Mededinging, samengesteld uit: de heer Frank Deschoolmeester, kamervoorzitter ; de heren Peter Poma, Wouter  Devroe en Geert Zonnekeyn, leden.</p>",
      "page": 81,
      "polygon": [
        [
          71.0078125,
          465.44512939453125
        ],
        [
          527.234130859375,
          465.44512939453125
        ],
        [
          527.234130859375,
          502.19512939453125
        ],
        [
          71.0078125,
          502.19512939453125
        ]
      ],
      "bbox": [
        71.0078125,
        465.44512939453125,
        527.234130859375,
        502.19512939453125
      ],
      "section_hierarchy": {
        "1": "/page/2/SectionHeader/6"
      },
      "images": {}
    }
  ],
  "page_info": {
    "0": {
      "bbox": [
        0.0,
        0.0,
        596.0,
        842.0
      ],
      "polygon": [
        [
          0.0,
          0.0
        ],
        [
          596.0,
          0.0
        ],
        [
          596.0,
          842.0
        ],
        [
          0.0,
          842.0
        ]
      ]
    },
    "1": {
      "bbox": [
        0.0,
        0.0,
        596.0,
        842.0
      ],
      "polygon": [
        [
          0.0,
          0.0
        ],
        [
          596.0,
          0.0
        ],
        [
          596.0,
          842.0
        ],
        [
          0.0,
          842.0
        ]
      ]
    },
    "2": {
      "bbox": [
        0.0,
        0.0,
        596.0,
        842.0
      ],
      "polygon": [
        [
          0.0,
          0.0
        ],
        [
          596.0,
          0.0
        ],
        [
          596.0,
          842.0
        ],
        [
          0.0,
          842.0
        ]
      ]
    }
  }
}