{
  "blocks": [
    {
      "id": "/page/0/PageHeader/0",
      "block_type": "PageHeader",
      "html": "",
      "page": 624,
      "polygon": [
        [
          12.783203125000002,
          16.0341796875
        ],
        [
          102.38195037841797,
          16.0341796875
        ],
        [
          102.38195037841797,
          39.97174072265625
        ],
        [
          12.783203125000002,
          39.97174072265625
        ]
      ],
      "bbox": [
        12.783203125000002,
        16.0341796875,
        102.38195037841797,
        39.97174072265625
      ],
      "section_hierarchy": {},
      "images": {}
    },
    {
      "id": "/page/0/SectionHeader/1",
      "block_type": "SectionHeader",
      "html": "<h2><b>Aalborg</b> <b>Havn</b> <b>A/S</b> <b>did</b> <b>not</b> <b>violate</b> <b>the</b> <b>competition</b> <b>act</b> <b>in</b> <b>the</b> <b>sale</b> <b>of</b> <b>Østre</b> <b>Havn</b></h2>",
      "page": 624,
      "polygon": [
        [
          12.783203125000002,
          55.5029296875
        ],
        [
          570.9041137695312,
          55.5029296875
        ],
        [
          570.9041137695312,
          103.04193115234375
        ],
        [
          12.783203125000002,
          103.04193115234375
        ]
      ],
      "bbox": [
        12.783203125000002,
        55.5029296875,
        570.9041137695312,
        103.04193115234375
      ],
      "section_hierarchy": {
        "2": "/page/0/SectionHeader/1"
      },
      "images": {}
    },
    {
      "id": "/page/0/Text/2",
      "block_type": "Text",
      "html": "<p block-type=\"Text\">On November 25th the Danish Competition Council (DCC) has decided on a case regarding the sale of a property called Østre Havn placed in the city of Aalborg. The DCC found that the publicly owned Aalborg Havn A/S did not violate the Danish competition acts rules concerning state aid by selling Østre Havn to a price of 42,8 million DKK.</p>",
      "page": 624,
      "polygon": [
        [
          13.945312500000002,
          118.8173828125
        ],
        [
          561.6153564453125,
          118.8173828125
        ],
        [
          561.6153564453125,
          156.382080078125
        ],
        [
          13.945312500000002,
          156.382080078125
        ]
      ],
      "bbox": [
        13.945312500000002,
        118.8173828125,
        561.6153564453125,
        156.382080078125
      ],
      "section_hierarchy": {
        "2": "/page/0/SectionHeader/1"
      },
      "images": {}
    },
    {
      "id": "/page/0/Text/3",
      "block_type": "Text",
      "html": "<p block-type=\"Text\">The case originates from a complaint from a member of the Danish parliament, Per Clausen. Per Clausen argued that the property was sold to a price lower than the marked price. If the property was sold to a price lower than the market price, the sale could constitute a violation of the Danish rules regarding state aid since Aalborg Havn A/S was almost fully owned by the city of Aalborg.</p>",
      "page": 624,
      "polygon": [
        [
          12.783203125000002,
          173.498046875
        ],
        [
          567.4232788085938,
          173.498046875
        ],
        [
          567.4232788085938,
          222.833984375
        ],
        [
          12.783203125000002,
          222.833984375
        ]
      ],
      "bbox": [
        12.783203125000002,
        173.498046875,
        567.4232788085938,
        222.833984375
      ],
      "section_hierarchy": {
        "2": "/page/0/SectionHeader/1"
      },
      "images": {}
    },
    {
      "id": "/page/0/Text/4",
      "block_type": "Text",
      "html": "<p block-type=\"Text\">The Danish Competition Authorities obtained an evaluation of Østre Havn carried out by an independent asset valuer. The valuer found that Østre Havn was worth 71,7 million DKK at the time of the sale. However, the valuer also found that the estimated market price was within a price range of 35-50 pct. and that a purchase price of app. 40-100 million DKK for that reason was to be regarded as the market price at the time of the sale.</p>",
      "page": 624,
      "polygon": [
        [
          13.945312500000002,
          238.0458984375
        ],
        [
          554.7899169921875,
          238.0458984375
        ],
        [
          554.7899169921875,
          288.92852783203125
        ],
        [
          13.945312500000002,
          288.92852783203125
        ]
      ],
      "bbox": [
        13.945312500000002,
        238.0458984375,
        554.7899169921875,
        288.92852783203125
      ],
      "section_hierarchy": {
        "2": "/page/0/SectionHeader/1"
      },
      "images": {}
    },
    {
      "id": "/page/0/Text/5",
      "block_type": "Text",
      "html": "<p block-type=\"Text\">The valuer found that it was not possible to reduce the extraordinarily wide price margin. This was due to unusually large uncertainties and exceptional circumstances related to the sale of Østre Havn.</p>",
      "page": 624,
      "polygon": [
        [
          12.783203125000002,
          304.23828125
        ],
        [
          553.763427734375,
          304.23828125
        ],
        [
          553.763427734375,
          328.69244384765625
        ],
        [
          12.783203125000002,
          328.69244384765625
        ]
      ],
      "bbox": [
        12.783203125000002,
        304.23828125,
        553.763427734375,
        328.69244384765625
      ],
      "section_hierarchy": {
        "2": "/page/0/SectionHeader/1"
      },
      "images": {}
    },
    {
      "id": "/page/0/Text/6",
      "block_type": "Text",
      "html": "<p block-type=\"Text\">The DCC found on the basis of the valuer's findings that it could not be refused that Østre Havn was sold at the market price. Therefore, Aalborg Havn A/S did not violate the Danish competition acts rules concerning state aid.</p>",
      "page": 624,
      "polygon": [
        [
          12.783203125000002,
          345.3515625
        ],
        [
          560.3150024414062,
          345.3515625
        ],
        [
          560.3150024414062,
          368.4563903808594
        ],
        [
          12.783203125000002,
          368.4563903808594
        ]
      ],
      "bbox": [
        12.783203125000002,
        345.3515625,
        560.3150024414062,
        368.4563903808594
      ],
      "section_hierarchy": {
        "2": "/page/0/SectionHeader/1"
      },
      "images": {}
    }
  ],
  "page_info": {
    "0": {
      "bbox": [
        0.0,
        0.0,
        595.0,
        842.0
      ],
      "polygon": [
        [
          0.0,
          0.0
        ],
        [
          595.0,
          0.0
        ],
        [
          595.0,
          842.0
        ],
        [
          0.0,
          842.0
        ]
      ]
    }
  }
}