{
  "blocks": [
    {
      "id": "/page/0/SectionHeader/0",
      "block_type": "SectionHeader",
      "html": "",
      "page": 233,
      "polygon": [
        [
          245.61718749999997,
          48.1025390625
        ],
        [
          348.0546875,
          48.1025390625
        ],
        [
          348.0546875,
          58.783447265625
        ],
        [
          245.61718749999997,
          58.783447265625
        ]
      ],
      "bbox": [
        245.61718749999997,
        48.1025390625,
        348.0546875,
        58.783447265625
      ],
      "section_hierarchy": {
        "4": "/page/0/SectionHeader/0"
      },
      "images": {}
    },
    {
      "id": "/page/0/SectionHeader/1",
      "block_type": "SectionHeader",
      "html": "<h2><b>AUTORITE BELGE DE LA CONCURRENCE</b></h2>",
      "page": 233,
      "polygon": [
        [
          153.65625,
          72.5595703125
        ],
        [
          440.735595703125,
          72.5595703125
        ],
        [
          440.735595703125,
          86.59954833984375
        ],
        [
          153.65625,
          86.59954833984375
        ]
      ],
      "bbox": [
        153.65625,
        72.5595703125,
        440.735595703125,
        86.59954833984375
      ],
      "section_hierarchy": {
        "2": "/page/0/SectionHeader/1"
      },
      "images": {}
    },
    {
      "id": "/page/0/SectionHeader/2",
      "block_type": "SectionHeader",
      "html": "<h2><b>Auditorat</b></h2>",
      "page": 233,
      "polygon": [
        [
          269.771484375,
          99.9052734375
        ],
        [
          324.2900085449219,
          99.9052734375
        ],
        [
          324.2900085449219,
          112.40008544921875
        ],
        [
          269.771484375,
          112.40008544921875
        ]
      ],
      "bbox": [
        269.771484375,
        99.9052734375,
        324.2900085449219,
        112.40008544921875
      ],
      "section_hierarchy": {
        "2": "/page/0/SectionHeader/2"
      },
      "images": {}
    },
    {
      "id": "/page/0/SectionHeader/3",
      "block_type": "SectionHeader",
      "html": "<h3><b>Décision n° ABC-2015-P/K-06-AUD du</b> <b>18</b> <b>mars</b> <b>2015</b></h3>",
      "page": 233,
      "polygon": [
        [
          149.58203125,
          138.2000732421875
        ],
        [
          444.4779968261719,
          138.2000732421875
        ],
        [
          444.4779968261719,
          150.2000732421875
        ],
        [
          149.58203125,
          150.2000732421875
        ]
      ],
      "bbox": [
        149.58203125,
        138.2000732421875,
        444.4779968261719,
        150.2000732421875
      ],
      "section_hierarchy": {
        "2": "/page/0/SectionHeader/2",
        "3": "/page/0/SectionHeader/3"
      },
      "images": {}
    },
    {
      "id": "/page/0/Text/4",
      "block_type": "Text",
      "html": "<p block-type=\"Text\"><i>Affaire Conc-P/K-12/0015</i> <i>–</i> <i>Comptoir de Russie SPRL</i> <i>contre Régie du Travail </i> <i>Pénitentiaire, Entente Wallonne des Entreprises de Travail Adapté ASBL, </i> <i>Fédération Bruxelloise des Entreprises de Travail Adapté ASBL et Vlaamse </i> <i>Federatie van Beschutte Werkplaatsen vzw</i></p>",
      "page": 233,
      "polygon": [
        [
          76.828125,
          164.00006103515625
        ],
        [
          523.8619995117188,
          164.00006103515625
        ],
        [
          523.8619995117188,
          217.4892578125
        ],
        [
          76.828125,
          217.4892578125
        ]
      ],
      "bbox": [
        76.828125,
        164.00006103515625,
        523.8619995117188,
        217.4892578125
      ],
      "section_hierarchy": {
        "2": "/page/0/SectionHeader/2",
        "3": "/page/0/SectionHeader/3"
      },
      "images": {}
    },
    {
      "id": "/page/0/SectionHeader/5",
      "block_type": "SectionHeader",
      "html": "<h2><b>1. Procédure</b></h2>",
      "page": 233,
      "polygon": [
        [
          69.84375,
          283.57427978515625
        ],
        [
          155.76119995117188,
          283.57427978515625
        ],
        [
          155.76119995117188,
          297.6142578125
        ],
        [
          69.84375,
          297.6142578125
        ]
      ],
      "bbox": [
        69.84375,
        283.57427978515625,
        155.76119995117188,
        297.6142578125
      ],
      "section_hierarchy": {
        "2": "/page/0/SectionHeader/5"
      },
      "images": {}
    },
    {
      "id": "/page/0/ListGroup/233",
      "block_type": "ListGroup",
      "html": "<p block-type=\"ListGroup\"><ul><li block-type=\"ListItem\">1. La SPRL Comptoir de Russie a introduit le 6 juillet 2012 auprès de l'Auditorat du  Conseil de la concurrence une plainte assortie d'une demande de mesures provisoires conformément aux articles IV.41, §1, 2° et IV.64 du Code de droit économique (ci-après  CDE) (ex articles 44, § 1, 2° et 62 de la loi sur la protection de la concurrence  économique coordonnée le 15 septembre 2006, ci-après la LPCE) dirigée contre la Régie  du Travail Pénitentiaire (le Service Central de la Régie du Travail Pénitentiaire ci-après,  la <i>«</i> <i>SCRTP</i> <i>»</i>), l'Entente Wallonne des Entreprises de Travail Adapté ASBL (ci-après,  <i>«</i> <i>l'EWETA</i> <i>»</i>), la Fédération Bruxelloise des Entreprises de Travail Adapté ASBL (ciaprès, la <i>«</i> <i>FEBRAP</i> <i>»</i>) et la Vlaamse Federatie van Beschutte Werkplaatsen vzw (ciaprès, la <i>«</i> <i>VLAB</i> <i>»</i>) (ci-après « les Fédérations d'ETA» pour l'ensemble des trois  associations sans but lucratif). La plainte concernait une entente entre la SCRTP et les  Fédérations d'ETA, ayant pris la forme d'une « Convention de Collaboration » signée le  3 mai 2011, en infraction avec l'article 2 de la LPCE.</li><li block-type=\"ListItem\">2. La plainte et la demande de mesures provisoires ont été enregistrées respectivement sous  les références CONC-P/K-12/0015 et CONC-V/M-12/0016.</li><li block-type=\"ListItem\">3. Dans une lettre transmise le 12 septembre 2012, le conseil des Fédérations d'ETA a  demandé pour ses clients de poursuivre l'instruction de l'affaire en néerlandais.</li><li block-type=\"ListItem\">4. Par courrier recommandé du 15 octobre 2012, l'auditeur a informé le conseil des  Fédérations d'ETA que l'instruction de la plainte ainsi que de la demande de mesures  provisoires serait poursuivie en français en application de l'article 93, alinéa 3 de la  LPCE.</li><li block-type=\"ListItem\">5. En effet, dans la présente affaire, une association d'entreprises est établie en Région  wallonne (l'EWETA), une autre en Région flamande (la VLAB) et la dernière en Région  bruxelloise (FEBRAP). La SCRTP est quant à elle également établie en Région  bruxelloise. Parmi ces deux dernières, seule la FEBRAP a demandé le changement de la  langue de procédure (vers le néerlandais) en application de l'article 93 al. 3 de la LPCE.  L'hypothèse de parité prévue par l'art. 93 al. 1 de la LPCE est bien rencontrée en  l'espèce et l'usage de l'une des langues nationales se détermine selon les besoins de la  cause. Dans la mesure où le plaignant est établi en Région bruxelloise et a choisi le</li></ul></p>",
      "page": 233,
      "polygon": [
        [
          75.6640625,
          315.75
        ],
        [
          527.511962890625,
          315.75
        ],
        [
          527.511962890625,
          767.99609375
        ],
        [
          75.6640625,
          767.99609375
        ]
      ],
      "bbox": [
        75.6640625,
        315.75,
        527.511962890625,
        767.99609375
      ],
      "section_hierarchy": {
        "2": "/page/0/SectionHeader/5"
      },
      "images": {}
    },
    {
      "id": "/page/1/SectionHeader/0",
      "block_type": "SectionHeader",
      "html": "",
      "page": 216,
      "polygon": [
        [
          247.489990234375,
          48.1025390625
        ],
        [
          348.345703125,
          48.1025390625
        ],
        [
          348.345703125,
          58.783447265625
        ],
        [
          247.489990234375,
          58.783447265625
        ]
      ],
      "bbox": [
        247.489990234375,
        48.1025390625,
        348.345703125,
        58.783447265625
      ],
      "section_hierarchy": {
        "2": "/page/0/SectionHeader/5",
        "4": "/page/1/SectionHeader/0"
      },
      "images": {}
    },
    {
      "id": "/page/1/ListGroup/214",
      "block_type": "ListGroup",
      "html": "<p block-type=\"ListGroup\"><ul><li block-type=\"ListItem\">français comme langue utilisée en application de l'article 93 al. 2 de la LPCE, il  n'existait pas de raison de poursuivre l'instruction dans une autre langue que le français.</li><li block-type=\"ListItem\">6. Dans une décision n° 2013-V/M-07 du 5 mars 2013 en langue française, le Président du  Conseil de la concurrence rejette la demande de mesures provisoires, les conditions  imposées par l'article 62 de la LPCE n'étant pas réunies. Cette décision de rejet de  mesures provisoires fait suite à la décision des Fédérations d'ETA de mettre fin  unilatéralement à la convention du 3 mai 2011, qui constitue précisément l'objet de la  plainte.</li><li block-type=\"ListItem\">7. Le 6 septembre 2013, la Loi portant insertion du livre IV « Protection de la  concurrence » dans le Code de droit économique est entrée en vigueur.</li></ul></p>",
      "page": 216,
      "polygon": [
        [
          75.6640625,
          71.9482421875
        ],
        [
          527.4639892578125,
          71.9482421875
        ],
        [
          527.4639892578125,
          235.84149169921875
        ],
        [
          75.6640625,
          235.84149169921875
        ]
      ],
      "bbox": [
        75.6640625,
        71.9482421875,
        527.4639892578125,
        235.84149169921875
      ],
      "section_hierarchy": {
        "2": "/page/0/SectionHeader/5",
        "4": "/page/1/SectionHeader/0"
      },
      "images": {}
    },
    {
      "id": "/page/1/SectionHeader/4",
      "block_type": "SectionHeader",
      "html": "<h2><b>2. Description des entreprises concernées </b></h2>",
      "page": 216,
      "polygon": [
        [
          70.42578125,
          290.6708984375
        ],
        [
          356.3927917480469,
          290.6708984375
        ],
        [
          356.3927917480469,
          305.5343017578125
        ],
        [
          70.42578125,
          305.5343017578125
        ]
      ],
      "bbox": [
        70.42578125,
        290.6708984375,
        356.3927917480469,
        305.5343017578125
      ],
      "section_hierarchy": {
        "2": "/page/1/SectionHeader/4"
      },
      "images": {}
    },
    {
      "id": "/page/1/SectionHeader/5",
      "block_type": "SectionHeader",
      "html": "<h2><i>2.1. La Partie plaignante</i></h2>",
      "page": 216,
      "polygon": [
        [
          70.8239974975586,
          321.505859375
        ],
        [
          208.94921875,
          321.505859375
        ],
        [
          208.94921875,
          334.31011962890625
        ],
        [
          70.8239974975586,
          334.31011962890625
        ]
      ],
      "bbox": [
        70.8239974975586,
        321.505859375,
        208.94921875,
        334.31011962890625
      ],
      "section_hierarchy": {
        "2": "/page/1/SectionHeader/5"
      },
      "images": {}
    },
    {
      "id": "/page/1/ListGroup/215",
      "block_type": "ListGroup",
      "html": "<p block-type=\"ListGroup\"><ul><li block-type=\"ListItem\">8. La <b>SPRL Comptoir de Russie</b>, ayant son siège social Avenue Montjoie 58 à 1180  Uccle et inscrite auprès de la Banque Carrefour des Entreprises sous le n° 0464.166.279,  est une société commerciale active dans la fourniture de biens et de services. Elle exerce  ses activités sous la dénomination commerciale « national2international » (en abrégé « n2i »).</li><li block-type=\"ListItem\">9. Depuis 2008, n2i agit comme intermédiaire entre, d'une part, ses propres clients qui  concluent des contrats d'entreprise avec elle en vue de l'exécution de prestations  manuelles peu qualifiées et habituellement externalisées par les entreprises en question et, d'autre part, les ateliers des prisons qui relèvent de l'autorité de la SCRTP et qui  effectuent les prestations susmentionnées. Dans ce cadre, n2i assure également, avec  l'accord de la SCRTP, un rôle de coordination afin de garantir l'exécution conforme de  la sous-traitance par la SCRTP au profit des clients finaux.</li></ul></p>",
      "page": 216,
      "polygon": [
        [
          76.828125,
          350.4714660644531
        ],
        [
          527.5,
          350.4714660644531
        ],
        [
          527.5,
          527.9714660644531
        ],
        [
          76.828125,
          527.9714660644531
        ]
      ],
      "bbox": [
        76.828125,
        350.4714660644531,
        527.5,
        527.9714660644531
      ],
      "section_hierarchy": {
        "2": "/page/1/SectionHeader/5"
      },
      "images": {}
    },
    {
      "id": "/page/1/SectionHeader/8",
      "block_type": "SectionHeader",
      "html": "<h3><i>2.2. Les entreprises concernées</i> <i>par l'instruction</i></h3>",
      "page": 216,
      "polygon": [
        [
          70.8239974975586,
          555.7301025390625
        ],
        [
          346.9460144042969,
          555.7301025390625
        ],
        [
          346.9460144042969,
          567.7744140625
        ],
        [
          70.8239974975586,
          567.7744140625
        ]
      ],
      "bbox": [
        70.8239974975586,
        555.7301025390625,
        346.9460144042969,
        567.7744140625
      ],
      "section_hierarchy": {
        "2": "/page/1/SectionHeader/5",
        "3": "/page/1/SectionHeader/8"
      },
      "images": {}
    },
    {
      "id": "/page/1/ListGroup/216",
      "block_type": "ListGroup",
      "html": "<p block-type=\"ListGroup\"><ul><li block-type=\"ListItem\">10. Le <b>Service Central de la Régie du Travail Pénitentiaire (SCRTP)</b>, ayant son siège  social à Quai de Willebroeck 33 à 1000 Bruxelles et inscrite auprès de la Banque  Carrefour des Entreprises sous le n° 0307.584.129, est un service public à gestion  autonome qui s'occupe de la mise au travail des détenus.</li><li block-type=\"ListItem\">11. Chaque établissement pénitentiaire dispose d'ateliers industriels : ces espaces de travail  sont principalement destinés à la mise à disposition de main d'œuvre aux entreprises  désireuses d'effectuer, de manière ponctuelle ou plus régulière, certains travaux en dehors de leurs propres installations. La nature des travaux est très variée : emballage,  pliage, montage, découpe, collage, mise sous pli, conditionnement, manutention, soustraitances industrielles diverses, façonnage, assemblage, cartonnage, encartage,  montages électriques, encodage de données, scanning de documents, triage, etc. Il existe</li></ul></p>",
      "page": 216,
      "polygon": [
        [
          77.90399932861328,
          583.9214782714844
        ],
        [
          527.4760131835938,
          583.9214782714844
        ],
        [
          527.4760131835938,
          747.8505859375
        ],
        [
          77.90399932861328,
          747.8505859375
        ]
      ],
      "bbox": [
        77.90399932861328,
        583.9214782714844,
        527.4760131835938,
        747.8505859375
      ],
      "section_hierarchy": {
        "2": "/page/1/SectionHeader/5",
        "3": "/page/1/SectionHeader/8"
      },
      "images": {}
    },
    {
      "id": "/page/1/PageFooter/11",
      "block_type": "PageFooter",
      "html": "",
      "page": 216,
      "polygon": [
        [
          518.0078125,
          794.7197265625
        ],
        [
          524.9921875,
          794.7197265625
        ],
        [
          524.9921875,
          805.5434112548828
        ],
        [
          518.0078125,
          805.5434112548828
        ]
      ],
      "bbox": [
        518.0078125,
        794.7197265625,
        524.9921875,
        805.5434112548828
      ],
      "section_hierarchy": {
        "2": "/page/1/SectionHeader/5",
        "3": "/page/1/SectionHeader/8"
      },
      "images": {}
    },
    {
      "id": "/page/2/SectionHeader/0",
      "block_type": "SectionHeader",
      "html": "",
      "page": 247,
      "polygon": [
        [
          247.36328124999997,
          48.82342529296875
        ],
        [
          348.63671875,
          48.82342529296875
        ],
        [
          348.63671875,
          58.783447265625
        ],
        [
          247.36328124999997,
          58.783447265625
        ]
      ],
      "bbox": [
        247.36328124999997,
        48.82342529296875,
        348.63671875,
        58.783447265625
      ],
      "section_hierarchy": {
        "2": "/page/1/SectionHeader/5",
        "3": "/page/1/SectionHeader/8",
        "4": "/page/2/SectionHeader/0"
      },
      "images": {}
    },
    {
      "id": "/page/2/Text/1",
      "block_type": "Text",
      "html": "<p block-type=\"Text\">également des ateliers dédiés à un type bien précis d'activité industrielle, tels que :  menuiserie, forge, couture, imprimerie et exploitation agricole.</p>",
      "page": 247,
      "polygon": [
        [
          95.453125,
          71.9482421875
        ],
        [
          527.4999389648438,
          71.9482421875
        ],
        [
          527.4999389648438,
          97.84149169921875
        ],
        [
          95.453125,
          97.84149169921875
        ]
      ],
      "bbox": [
        95.453125,
        71.9482421875,
        527.4999389648438,
        97.84149169921875
      ],
      "section_hierarchy": {
        "2": "/page/1/SectionHeader/5",
        "3": "/page/1/SectionHeader/8",
        "4": "/page/2/SectionHeader/0"
      },
      "images": {}
    },
    {
      "id": "/page/2/ListGroup/246",
      "block_type": "ListGroup",
      "html": "<p block-type=\"ListGroup\"><ul><li block-type=\"ListItem\">12.  L'<b>Entente Wallonne des Entreprises de Travail Adapté ASBL</b>, ayant son siège  social à Route de Philippeville 196 à 6010 Couillet et inscrite auprès de la Banque  Carrefour des Entreprises sous le n° 0418.788.788, <ul><li block-type=\"ListItem\" class=\"list-indent-1\"> la <b>Fédération Bruxelloise des Entreprises de Travail Adapté ASBL</b>, ayant son  siège social à Trassersweg 347 à 1120 Bruxelles et inscrite auprès de la Banque  Carrefour des Entreprises sous le n° 0444.913.363,</li></ul><ul><li block-type=\"ListItem\" class=\"list-indent-1\"> la <b>Vlaamse Federatie van Beschutte Werkplaatsen vzw</b>, ayant son siège social à Goossensvest 34 à 3300 Tienen et inscrite auprès de la Banque Carrefour des Entreprises  sous le n° 0421.292.675,</li></ul></li></ul></p>",
      "page": 247,
      "polygon": [
        [
          76.828125,
          113.44146728515625
        ],
        [
          527.4639892578125,
          113.44146728515625
        ],
        [
          527.4639892578125,
          263.47149658203125
        ],
        [
          76.828125,
          263.47149658203125
        ]
      ],
      "bbox": [
        76.828125,
        113.44146728515625,
        527.4639892578125,
        263.47149658203125
      ],
      "section_hierarchy": {
        "2": "/page/1/SectionHeader/5",
        "3": "/page/1/SectionHeader/8",
        "4": "/page/2/SectionHeader/0"
      },
      "images": {}
    },
    {
      "id": "/page/2/Text/5",
      "block_type": "Text",
      "html": "<p block-type=\"Text\">ci-après conjointement « les Fédérations d'ETA», sont des associations d'entreprises  constituées par les anciens ateliers protégés - devenus entreprises de travail adapté (ciaprès, <i>«</i> <i>ETA</i> <i>»</i>) en 1995 - désirant se rassembler au sein d'une association  professionnelle en vue de défendre les intérêts des ETA aux niveaux juridique,  économique et social et par là même des travailleurs handicapés qu'elles emploient.</p>",
      "page": 247,
      "polygon": [
        [
          94.2890625,
          279.07147216796875
        ],
        [
          527.3619995117188,
          279.07147216796875
        ],
        [
          527.3619995117188,
          346.2714538574219
        ],
        [
          94.2890625,
          346.2714538574219
        ]
      ],
      "bbox": [
        94.2890625,
        279.07147216796875,
        527.3619995117188,
        346.2714538574219
      ],
      "section_hierarchy": {
        "2": "/page/1/SectionHeader/5",
        "3": "/page/1/SectionHeader/8",
        "4": "/page/2/SectionHeader/0"
      },
      "images": {}
    },
    {
      "id": "/page/2/SectionHeader/6",
      "block_type": "SectionHeader",
      "html": "<h2><b>3. Les Faits</b></h2>",
      "page": 247,
      "polygon": [
        [
          70.42578125,
          401.914306640625
        ],
        [
          146.76011657714844,
          401.914306640625
        ],
        [
          146.76011657714844,
          415.9543151855469
        ],
        [
          70.42578125,
          415.9543151855469
        ]
      ],
      "bbox": [
        70.42578125,
        401.914306640625,
        146.76011657714844,
        415.9543151855469
      ],
      "section_hierarchy": {
        "2": "/page/2/SectionHeader/6"
      },
      "images": {}
    },
    {
      "id": "/page/2/ListGroup/247",
      "block_type": "ListGroup",
      "html": "<p block-type=\"ListGroup\"><ul><li block-type=\"ListItem\">13. n2i collabore avec la SCRTP depuis 2008. Progressivement, n2i a augmenté le nombre  des contrats de sous-traitance conclus avec la SCRTP, tout en restant un acteur modeste  au regard du volume d'activités générées par la SCRTP et les ETA.</li><li block-type=\"ListItem\">14. Un Business Process Reengineering (BPR) réalisé en interne par le Service public  fédéral Justice a fait apparaître que la SCRTP devait mener une politique plus  commerciale et axée sur le client afin de mettre au travail le plus grand nombre possible  de détenus de manière optimale. Le principal changement est la création d'un niveau  « méso », chaque entité « méso » étant responsable de cinq à sept prisons. Chaque  « méso » dispose d'une équipe commerciale chargée d'explorer le marché pour recruter  des entrepreneurs susceptibles de mettre les détenus au travail et établit le planning de  production pour les prisons. La procédure de recrutement interne de membres du  personnel pour les six nouveaux services de ce type a été lancée en septembre 2010. Le  lancement des sites pilotes est intervenu dans le courant 2011. En 2014, les six équipes  « méso » de Marneffe, Bruges, Lantin, Hasselt, Ittre et Merkplas étaient actives.</li><li block-type=\"ListItem\">15. Parallèlement des discussions ont eu lieu entre la SCRTP et les ETA en vue <i>«</i> <i>d'unir </i> <i>leurs efforts dans le but d'une part, d'éviter toute concurrence et d'autre part, de </i> <i>collaborer en toute transparence sur certains marchés.</i> <i>»</i> (cf. Rapport d'activité de la  DG Etablissements pénitentiaires 2010).</li><li block-type=\"ListItem\">16. Les discussions susmentionnées ont abouti le 3 mai 2011 à une convention de  collaboration entre la SCRTP et les Fédérations d'ETA.</li></ul></p>",
      "page": 247,
      "polygon": [
        [
          76.828125,
          434.3714599609375
        ],
        [
          527.5120239257812,
          434.3714599609375
        ],
        [
          527.5120239257812,
          750.0214614868164
        ],
        [
          76.828125,
          750.0214614868164
        ]
      ],
      "bbox": [
        76.828125,
        434.3714599609375,
        527.5120239257812,
        750.0214614868164
      ],
      "section_hierarchy": {
        "2": "/page/2/SectionHeader/6"
      },
      "images": {}
    },
    {
      "id": "/page/2/PageFooter/11",
      "block_type": "PageFooter",
      "html": "",
      "page": 247,
      "polygon": [
        [
          518.298828125,
          794.7197265625
        ],
        [
          524.701171875,
          794.7197265625
        ],
        [
          524.701171875,
          805.5434112548828
        ],
        [
          518.298828125,
          805.5434112548828
        ]
      ],
      "bbox": [
        518.298828125,
        794.7197265625,
        524.701171875,
        805.5434112548828
      ],
      "section_hierarchy": {
        "2": "/page/2/SectionHeader/6"
      },
      "images": {}
    },
    {
      "id": "/page/3/SectionHeader/0",
      "block_type": "SectionHeader",
      "html": "",
      "page": 268,
      "polygon": [
        [
          246.49023437499997,
          48.1025390625
        ],
        [
          347.6776123046875,
          48.1025390625
        ],
        [
          347.6776123046875,
          58.783447265625
        ],
        [
          246.49023437499997,
          58.783447265625
        ]
      ],
      "bbox": [
        246.49023437499997,
        48.1025390625,
        347.6776123046875,
        58.783447265625
      ],
      "section_hierarchy": {
        "2": "/page/2/SectionHeader/6",
        "4": "/page/3/SectionHeader/0"
      },
      "images": {}
    },
    {
      "id": "/page/3/ListGroup/267",
      "block_type": "ListGroup",
      "html": "<p block-type=\"ListGroup\"><ul><li block-type=\"ListItem\">17. L'article 2 de la convention précise les modalités de collaboration et, notamment, prévoit  que :  <ul><li block-type=\"ListItem\" class=\"list-indent-1\"><i>«</i><i>§1. La Régie du Travail Pénitentiaire et les fédérations patronales d'entreprises de </i> <i>travail adapté unissent leurs ef</i><i>forts dans le but d'éviter une concurrence plus intense </i> <i>et d'obtenir une collaboration entre les deux secteurs.</i></li></ul><ul><li block-type=\"ListItem\" class=\"list-indent-1\"><i>§2. L</i>es <i>fédérations patronales d'entreprises de travail adapté</i> <i>(</i> <i>…</i>) <i>s'engagent à collaborer en toute transparence avec le Service Central de </i><i>la Régie du </i> <i>Travail Pénitentiaire, et en particulier</i> <i>:</i></li></ul><ul><li block-type=\"ListItem\" class=\"list-indent-1\"><i>-</i> <i>à communiquer au SCRTP, dans les plus courts délais, les noms des clients perdus </i> <i>au profit des prisons ou des intermédiaires</i> <i>;</i></li></ul><ul><li block-type=\"ListItem\" class=\"list-indent-1\"><i>-</i> <i>à</i> <i>avertir</i> <i>la Régie en cas de concurrence potentielle sur un marché</i> <i>;</i></li></ul><ul><li block-type=\"ListItem\" class=\"list-indent-1\"><i>-</i> <i>à ne pas prendre</i> <i>un marché déjà attribué à une prison.</i></li></ul><ul><li block-type=\"ListItem\" class=\"list-indent-1\"><i>§3. La Régie du Travail Pénitentiaire s'engage à collaborer en toute transparence </i> <i>avec les fédérations patronales d'entreprises de travail adapté et leurs membres. </i> <i>Concrètement, la Régie du Travail P</i><i>énitentiaire s'engage</i> <i>:</i></li></ul><ul><li block-type=\"ListItem\" class=\"list-indent-1\"><i>-</i> <i>à indiquer sur ses offres de prix et sur ses contrats que ceux-ci sont nuls et non </i> <i>avenus</i> <i>si le travail relatif à cette remise de prix ou à ce contrat est déjà réalisé dans </i> <i>une entreprise de travail adapté</i> <i>;</i></li></ul><ul><li block-type=\"ListItem\" class=\"list-indent-1\"><i>-</i> <i>à ne pas accepter</i> <i>un</i> <i>marché, privé ou public, en sachant qu'il a été repris à une </i> <i>entreprise de travail adapté, ou à discuter</i> <i>avec le Directeur de l'ETA et </i><i>adapter sa </i> <i>politique tarifaire</i> <i>;</i></li></ul></li></ul></p>",
      "page": 268,
      "polygon": [
        [
          76.828125,
          99.0830078125
        ],
        [
          527.4760131835938,
          99.0830078125
        ],
        [
          527.4760131835938,
          415.6552734375
        ],
        [
          76.828125,
          415.6552734375
        ]
      ],
      "bbox": [
        76.828125,
        99.0830078125,
        527.4760131835938,
        415.6552734375
      ],
      "section_hierarchy": {
        "2": "/page/2/SectionHeader/6",
        "4": "/page/3/SectionHeader/0"
      },
      "images": {}
    },
    {
      "id": "/page/3/Text/10",
      "block_type": "Text",
      "html": "<p block-type=\"Text\"><i>(…)</i></p>",
      "page": 268,
      "polygon": [
        [
          109.712890625,
          416.8514709472656
        ],
        [
          128.8040008544922,
          416.8514709472656
        ],
        [
          128.8040008544922,
          428.8514709472656
        ],
        [
          109.712890625,
          428.8514709472656
        ]
      ],
      "bbox": [
        109.712890625,
        416.8514709472656,
        128.8040008544922,
        428.8514709472656
      ],
      "section_hierarchy": {
        "2": "/page/2/SectionHeader/6",
        "4": "/page/3/SectionHeader/0"
      },
      "images": {}
    },
    {
      "id": "/page/3/ListGroup/268",
      "block_type": "ListGroup",
      "html": "<p block-type=\"ListGroup\"><ul><li block-type=\"ListItem\"><i>-</i> <i>augmenter progressivement ses tarifs</i> <i>au fur et à mesure de l'implémentation du </i> <i>se</i><i>rvice commercial et appliquer l'indexation, afin de </i><i>réduire</i> <i>les distorsions tarifaires </i> <i>qui existent entre les deux secteurs, et à tendre autant que possible vers des prix </i> <i>compétitifs sur le marché, tant envers les entreprises privées que les marchés </i> <i>publics</i> <i>;</i></li><li block-type=\"ListItem\"><i>-</i> <i>identifier</i> <i>les</i> <i>intermédiaires</i> <i>et leurs clients finaux, dans la mesure du possible</i> <i>;</i></li><li block-type=\"ListItem\"><i>-</i> <i>réduire</i> <i>le</i> <i>recours</i> <i>aux</i> <i>intermédiaires</i><i>, grâce au développement de l'équipe </i> <i>commerciale du SCRTP.</i> <i>».</i></li><li block-type=\"ListItem\">18. Les Fédérations d'ETA ont mis fin à la convention du 3 mai 2011, par lettres de la  VLAB du 14 janvier 2013, de la FEBRAP du 7 février 2013, et de l'EWETA du 8  février 2013, soit quelques semaines ou jours avant l'audience devant le Président du  Conseil de la Concurrence relative à la demande de mesures provisoires de la Partie  Plaignante (voir point suivant).</li><li block-type=\"ListItem\">19. Malgré cette dénonciation de la convention par les Fédérations d'ETA, la SCRTP y fait  encore référence en 2013 et 2014 dans une note infrapaginale de certains de ses devis :  <i>«</i> <i>conformément à la convention du 3/5/2011 entre la RTP et les ETA, tout devis</i> <i>établi </i> <i>pour un travail qui est déjà réalisé au sein d'une ETA sera considéré comme nul et non </i> <i>avenu</i> <i>»</i>.</li><li block-type=\"ListItem\">20. Dans un mail du 27 février 2015 adressé à l'Autorité belge de la concurrence par le  conseil de la SCRTP, cette dernière <i>«</i> <i>confirme que la convention du 3 mai 2011 n'est </i></li></ul></p>",
      "page": 268,
      "polygon": [
        [
          75.6640625,
          430.6514587402344
        ],
        [
          527.5360107421875,
          430.6514587402344
        ],
        [
          527.5360107421875,
          743.4214630126953
        ],
        [
          75.6640625,
          743.4214630126953
        ]
      ],
      "bbox": [
        75.6640625,
        430.6514587402344,
        527.5360107421875,
        743.4214630126953
      ],
      "section_hierarchy": {
        "2": "/page/2/SectionHeader/6",
        "4": "/page/3/SectionHeader/0"
      },
      "images": {}
    },
    {
      "id": "/page/3/PageFooter/17",
      "block_type": "PageFooter",
      "html": "",
      "page": 268,
      "polygon": [
        [
          518.0078125,
          794.7197265625
        ],
        [
          524.9921875,
          794.7197265625
        ],
        [
          524.9921875,
          805.5434112548828
        ],
        [
          518.0078125,
          805.5434112548828
        ]
      ],
      "bbox": [
        518.0078125,
        794.7197265625,
        524.9921875,
        805.5434112548828
      ],
      "section_hierarchy": {
        "2": "/page/2/SectionHeader/6",
        "4": "/page/3/SectionHeader/0"
      },
      "images": {}
    },
    {
      "id": "/page/4/SectionHeader/0",
      "block_type": "SectionHeader",
      "html": "",
      "page": 205,
      "polygon": [
        [
          247.489990234375,
          48.1025390625
        ],
        [
          348.0546875,
          48.1025390625
        ],
        [
          348.0546875,
          58.783447265625
        ],
        [
          247.489990234375,
          58.783447265625
        ]
      ],
      "bbox": [
        247.489990234375,
        48.1025390625,
        348.0546875,
        58.783447265625
      ],
      "section_hierarchy": {
        "2": "/page/2/SectionHeader/6",
        "4": "/page/4/SectionHeader/0"
      },
      "images": {}
    },
    {
      "id": "/page/4/ListGroup/202",
      "block_type": "ListGroup",
      "html": "<p block-type=\"ListGroup\"><ul><li block-type=\"ListItem\"><i>plus d'application (1) et s'engage à supprimer toute référence à celle</i><i>-ci sur quelque </i> <i>support que ce soit (2)</i> <i>»</i>.</li><li block-type=\"ListItem\">21. Dans une décision n° 2013-V/M-07 du 5 mars 2013 en langue française, le Président du  Conseil de la concurrence rejette la demande de mesures provisoires, les conditions  imposées par l'article 62 de la LPCE n'étant pas réunies.</li></ul></p>",
      "page": 205,
      "polygon": [
        [
          76.828125,
          71.9482421875
        ],
        [
          527.4879760742188,
          71.9482421875
        ],
        [
          527.4879760742188,
          153.04150390625
        ],
        [
          76.828125,
          153.04150390625
        ]
      ],
      "bbox": [
        76.828125,
        71.9482421875,
        527.4879760742188,
        153.04150390625
      ],
      "section_hierarchy": {
        "2": "/page/2/SectionHeader/6",
        "4": "/page/4/SectionHeader/0"
      },
      "images": {}
    },
    {
      "id": "/page/4/SectionHeader/3",
      "block_type": "SectionHeader",
      "html": "<h2><b>4. Objet de la plainte</b></h2>",
      "page": 205,
      "polygon": [
        [
          68.970703125,
          208.4443359375
        ],
        [
          206.9573974609375,
          208.4443359375
        ],
        [
          206.9573974609375,
          222.70428466796875
        ],
        [
          68.970703125,
          222.70428466796875
        ]
      ],
      "bbox": [
        68.970703125,
        208.4443359375,
        206.9573974609375,
        222.70428466796875
      ],
      "section_hierarchy": {
        "2": "/page/4/SectionHeader/3"
      },
      "images": {}
    },
    {
      "id": "/page/4/ListGroup/203",
      "block_type": "ListGroup",
      "html": "<p block-type=\"ListGroup\"><ul><li block-type=\"ListItem\">22. La Partie Plaignante a formulé ses griefs à l'encontre des entreprises concernées de la  manière suivante : <ul><li block-type=\"ListItem\" class=\"list-indent-1\"><i>«</i> <i>Une entente, appelée «</i> <i>Convention de Collaboration</i> <i>» entre les</i> <i>quatre entreprises </i> <i>identifiées ci-dessus (</i><i>…</i><i>) a été signée en date du 3 mai 2011.</i> <i>Cette entente vise </i> <i>explicitement à contrôler et à se partager un marché spécifique sur le territoire belge.</i></li></ul></li></ul></p>",
      "page": 205,
      "polygon": [
        [
          76.828125,
          241.1514892578125
        ],
        [
          527.5120239257812,
          241.1514892578125
        ],
        [
          527.5120239257812,
          322.1514892578125
        ],
        [
          76.828125,
          322.1514892578125
        ]
      ],
      "bbox": [
        76.828125,
        241.1514892578125,
        527.5120239257812,
        322.1514892578125
      ],
      "section_hierarchy": {
        "2": "/page/4/SectionHeader/3"
      },
      "images": {}
    },
    {
      "id": "/page/4/Text/6",
      "block_type": "Text",
      "html": "<p block-type=\"Text\"><i>Cette intention est sans aucune ambiguïté et se manifeste de la manière suivante</i> <i>:</i></p>",
      "page": 205,
      "polygon": [
        [
          106.2199935913086,
          337.75146484375
        ],
        [
          499.21600341796875,
          337.75146484375
        ],
        [
          499.21600341796875,
          349.75146484375
        ],
        [
          106.2199935913086,
          349.75146484375
        ]
      ],
      "bbox": [
        106.2199935913086,
        337.75146484375,
        499.21600341796875,
        349.75146484375
      ],
      "section_hierarchy": {
        "2": "/page/4/SectionHeader/3"
      },
      "images": {}
    },
    {
      "id": "/page/4/ListGroup/204",
      "block_type": "ListGroup",
      "html": "<p block-type=\"ListGroup\"><ul><li block-type=\"ListItem\"><i>-</i> <i>limitation des effets de la concurrence entre les parties</i> <i>;</i></li><li block-type=\"ListItem\"><i>-</i> <i>partage du marché</i> <i>;</i></li><li block-type=\"ListItem\"><i>-</i> <i>identification en vue </i><i>de de l'éviction des acteurs concurre</i><i>ntiels du marché (tierce </i> <i>partie)</i> <i>;</i></li><li block-type=\"ListItem\"><i>-</i> <i>violation systématique des informations réputées confidentielles appartenant aux </i> <i>acteurs de la tierce partie</i> <i>;</i></li><li block-type=\"ListItem\"><i>-</i> <i>récupération de la clientèle des acteurs concurrentiels du marché</i> <i>;</i></li><li block-type=\"ListItem\"><i>-</i> <i>entente sur les prix du marché visant à un alignement à court ou moyen terme des </i> <i>conditions tarifaires entre les parties incriminées</i> <i>;</i></li><li block-type=\"ListItem\"><i>-</i> <i>organisation semestrielle de réunions entre les parties en vue d'affiner la bonne </i> <i>coordination du partage du marché</i> <i>.»</i></li></ul></p>",
      "page": 205,
      "polygon": [
        [
          103.6015625,
          365.3514709472656
        ],
        [
          509.6419982910156,
          365.3514709472656
        ],
        [
          509.6419982910156,
          515.560546875
        ],
        [
          103.6015625,
          515.560546875
        ]
      ],
      "bbox": [
        103.6015625,
        365.3514709472656,
        509.6419982910156,
        515.560546875
      ],
      "section_hierarchy": {
        "2": "/page/4/SectionHeader/3"
      },
      "images": {}
    },
    {
      "id": "/page/4/SectionHeader/14",
      "block_type": "SectionHeader",
      "html": "<h2><b>5. Marché concerné</b></h2>",
      "page": 205,
      "polygon": [
        [
          69.552734375,
          571.0243225097656
        ],
        [
          201.4739990234375,
          571.0243225097656
        ],
        [
          201.4739990234375,
          585.0643310546875
        ],
        [
          69.552734375,
          585.0643310546875
        ]
      ],
      "bbox": [
        69.552734375,
        571.0243225097656,
        201.4739990234375,
        585.0643310546875
      ],
      "section_hierarchy": {
        "2": "/page/4/SectionHeader/14"
      },
      "images": {}
    },
    {
      "id": "/page/4/SectionHeader/15",
      "block_type": "SectionHeader",
      "html": "<h3><i>5.1. Le marché</i> <i>de produits</i></h3>",
      "page": 205,
      "polygon": [
        [
          69.84375,
          601.840087890625
        ],
        [
          222.79998779296875,
          601.840087890625
        ],
        [
          222.79998779296875,
          613.840087890625
        ],
        [
          69.84375,
          613.840087890625
        ]
      ],
      "bbox": [
        69.84375,
        601.840087890625,
        222.79998779296875,
        613.840087890625
      ],
      "section_hierarchy": {
        "2": "/page/4/SectionHeader/14",
        "3": "/page/4/SectionHeader/15"
      },
      "images": {}
    },
    {
      "id": "/page/4/ListGroup/205",
      "block_type": "ListGroup",
      "html": "<p block-type=\"ListGroup\"><ul><li block-type=\"ListItem\">23. Au niveau de l'offre, les entreprises de travail adapté confient à leurs travailleurs  principalement trois catégories d'activités manuelles peu qualifiées : <ul><li block-type=\"ListItem\" class=\"list-indent-1\"><b>(i) </b>sous-traitance dans les secteurs du conditionnement, de la paletterie, de  l'électronique, du câblage, de la mécano soudure, du mailing, du textile ;</li></ul><ul><li block-type=\"ListItem\" class=\"list-indent-1\"><b>(ii) </b>production propre dans les secteurs de l'imprimerie, du mobilier, de l'artisanat, de  la sylviculture, de la pisciculture, de l'élevage, de la maroquinerie ;</li></ul></li></ul></p>",
      "page": 205,
      "polygon": [
        [
          76.828125,
          629.033203125
        ],
        [
          527.385986328125,
          629.033203125
        ],
        [
          527.385986328125,
          739.216796875
        ],
        [
          76.828125,
          739.216796875
        ]
      ],
      "bbox": [
        76.828125,
        629.033203125,
        527.385986328125,
        739.216796875
      ],
      "section_hierarchy": {
        "2": "/page/4/SectionHeader/14",
        "3": "/page/4/SectionHeader/15"
      },
      "images": {}
    },
    {
      "id": "/page/4/PageFooter/19",
      "block_type": "PageFooter",
      "html": "",
      "page": 205,
      "polygon": [
        [
          518.298828125,
          794.7197265625
        ],
        [
          524.701171875,
          794.7197265625
        ],
        [
          524.701171875,
          805.5434112548828
        ],
        [
          518.298828125,
          805.5434112548828
        ]
      ],
      "bbox": [
        518.298828125,
        794.7197265625,
        524.701171875,
        805.5434112548828
      ],
      "section_hierarchy": {
        "2": "/page/4/SectionHeader/14",
        "3": "/page/4/SectionHeader/15"
      },
      "images": {}
    },
    {
      "id": "/page/5/SectionHeader/0",
      "block_type": "SectionHeader",
      "html": "",
      "page": 184,
      "polygon": [
        [
          247.489990234375,
          48.1025390625
        ],
        [
          348.0546875,
          48.1025390625
        ],
        [
          348.0546875,
          58.783447265625
        ],
        [
          247.489990234375,
          58.783447265625
        ]
      ],
      "bbox": [
        247.489990234375,
        48.1025390625,
        348.0546875,
        58.783447265625
      ],
      "section_hierarchy": {
        "2": "/page/4/SectionHeader/14",
        "3": "/page/4/SectionHeader/15",
        "4": "/page/5/SectionHeader/0"
      },
      "images": {}
    },
    {
      "id": "/page/5/Text/1",
      "block_type": "Text",
      "html": "<p block-type=\"Text\"><b>(iii) </b>fourniture de services dans les secteurs de l'Horeca, des parcs et jardins, de la  bureautique, des call center.</p>",
      "page": 184,
      "polygon": [
        [
          109.421875,
          71.9482421875
        ],
        [
          527.197998046875,
          71.9482421875
        ],
        [
          527.197998046875,
          97.84149169921875
        ],
        [
          109.421875,
          97.84149169921875
        ]
      ],
      "bbox": [
        109.421875,
        71.9482421875,
        527.197998046875,
        97.84149169921875
      ],
      "section_hierarchy": {
        "2": "/page/4/SectionHeader/14",
        "3": "/page/4/SectionHeader/15",
        "4": "/page/5/SectionHeader/0"
      },
      "images": {}
    },
    {
      "id": "/page/5/Text/2",
      "block_type": "Text",
      "html": "<p block-type=\"Text\">La sous-traitance couvre la plus grande partie des activités des ETA.</p>",
      "page": 184,
      "polygon": [
        [
          94.2890625,
          113.44146728515625
        ],
        [
          424.8828125,
          113.44146728515625
        ],
        [
          424.8828125,
          125.806640625
        ],
        [
          94.2890625,
          125.806640625
        ]
      ],
      "bbox": [
        94.2890625,
        113.44146728515625,
        424.8828125,
        125.806640625
      ],
      "section_hierarchy": {
        "2": "/page/4/SectionHeader/14",
        "3": "/page/4/SectionHeader/15",
        "4": "/page/5/SectionHeader/0"
      },
      "images": {}
    },
    {
      "id": "/page/5/ListGroup/183",
      "block_type": "ListGroup",
      "html": "<p block-type=\"ListGroup\"><ul><li block-type=\"ListItem\">24. La SCRTP quant à elle dispose d'un réseau de 33 ateliers répartis dans toute la Belgique  qui peuvent être mobilisés et coordonnés entre eux si nécessaire où elle permet aux  détenus pénitentiaires d'effectuer diverses tâches manuelles peu qualifiées dont la nature  est très variée : emballage, pliage, montage, découpe, collage, mise sous pli,  conditionnement, manutention, sous-traitances industrielles diverses, façonnage,  assemblage, cartonnage, encartage, montages électriques, encodage de données,  scanning de documents, triage, etc. Il existe également des ateliers spécialisés pour un  type bien précis d'activité dite industrielle, comme la menuiserie, la forge, la couture,  l'imprimerie et l'exploitation agricole.</li><li block-type=\"ListItem\">25. Au niveau de la demande, il existe d'une part, les entreprises qui sous-traitent  directement auprès de la SCRTP ou des ETA la réalisation de travaux ou de services  nécessitant peu de qualification et d'autre part les intermédiaires comme n2i qui soustraitent à la SCRTP ce même type de travaux et qui effectuent la prospection des clients  et le suivi des commandes.</li><li block-type=\"ListItem\">26. En conclusion, les activités exercées en sous-traitance par la SCRTP ou les ETA sont  multiples et relèvent de domaines très divers (agriculture, sylviculture, sous-traitance  industrielle, artisanat, informatique). Le facteur commun est le caractère d'activité  manuelle peu qualifiée.</li><li block-type=\"ListItem\">27. La définition de marché de produits est toutefois laissée ouverte dans la mesure où il  n'est pas nécessaire de se prononcer sur la question vu ce qui suit.</li></ul></p>",
      "page": 184,
      "polygon": [
        [
          75.6640625,
          137.7294921875
        ],
        [
          527.4879760742188,
          137.7294921875
        ],
        [
          527.4879760742188,
          452.1314392089844
        ],
        [
          75.6640625,
          452.1314392089844
        ]
      ],
      "bbox": [
        75.6640625,
        137.7294921875,
        527.4879760742188,
        452.1314392089844
      ],
      "section_hierarchy": {
        "2": "/page/4/SectionHeader/14",
        "3": "/page/4/SectionHeader/15",
        "4": "/page/5/SectionHeader/0"
      },
      "images": {}
    },
    {
      "id": "/page/5/SectionHeader/7",
      "block_type": "SectionHeader",
      "html": "<h2><i>5.2. Le marché géographique</i></h2>",
      "page": 184,
      "polygon": [
        [
          69.26171875,
          478.9697265625
        ],
        [
          236.77197265625,
          478.9697265625
        ],
        [
          236.77197265625,
          491.8901062011719
        ],
        [
          69.26171875,
          491.8901062011719
        ]
      ],
      "bbox": [
        69.26171875,
        478.9697265625,
        236.77197265625,
        491.8901062011719
      ],
      "section_hierarchy": {
        "2": "/page/5/SectionHeader/7"
      },
      "images": {}
    },
    {
      "id": "/page/5/ListGroup/184",
      "block_type": "ListGroup",
      "html": "<p block-type=\"ListGroup\"><ul><li block-type=\"ListItem\">28. Il ressort de l'instruction menée à l'occasion de la procédure en mesures provisoires que  tant les ETA que la SCRTP proposent leurs services sur l'ensemble du territoire belge.  Dans le même ordre d'idées, n2i fait appel, pour les besoins de sous-traitance, aux  différents ateliers de la SCRTP situés sur l'ensemble du territoire belge. Toutefois,  certaines de ces activités de sous-traitance sont également susceptibles d'être prestées à  l'étranger par des entreprises établies dans certains pays aux taux horaires bas.</li><li block-type=\"ListItem\">29. La définition de marché géographique est toutefois laissée ouverte dans la mesure où il  n'est pas nécessaire de se prononcer sur la question vu ce qui suit.</li></ul></p>",
      "page": 184,
      "polygon": [
        [
          75.6640625,
          508.5712890625
        ],
        [
          527.5,
          508.5712890625
        ],
        [
          527.5,
          632.7614593505859
        ],
        [
          75.6640625,
          632.7614593505859
        ]
      ],
      "bbox": [
        75.6640625,
        508.5712890625,
        527.5,
        632.7614593505859
      ],
      "section_hierarchy": {
        "2": "/page/5/SectionHeader/7"
      },
      "images": {}
    },
    {
      "id": "/page/5/PageFooter/10",
      "block_type": "PageFooter",
      "html": "",
      "page": 184,
      "polygon": [
        [
          518.298828125,
          794.30859375
        ],
        [
          524.701171875,
          794.30859375
        ],
        [
          524.701171875,
          805.5434112548828
        ],
        [
          518.298828125,
          805.5434112548828
        ]
      ],
      "bbox": [
        518.298828125,
        794.30859375,
        524.701171875,
        805.5434112548828
      ],
      "section_hierarchy": {
        "2": "/page/5/SectionHeader/7"
      },
      "images": {}
    },
    {
      "id": "/page/6/SectionHeader/0",
      "block_type": "SectionHeader",
      "html": "",
      "page": 232,
      "polygon": [
        [
          245.32617187499997,
          48.1025390625
        ],
        [
          347.6776123046875,
          48.1025390625
        ],
        [
          347.6776123046875,
          58.783447265625
        ],
        [
          245.32617187499997,
          58.783447265625
        ]
      ],
      "bbox": [
        245.32617187499997,
        48.1025390625,
        347.6776123046875,
        58.783447265625
      ],
      "section_hierarchy": {
        "2": "/page/5/SectionHeader/7",
        "4": "/page/6/SectionHeader/0"
      },
      "images": {}
    },
    {
      "id": "/page/6/SectionHeader/1",
      "block_type": "SectionHeader",
      "html": "<h2><b>6. En droit </b></h2>",
      "page": 232,
      "polygon": [
        [
          70.42578125,
          72.46435546875
        ],
        [
          143.19395446777344,
          72.46435546875
        ],
        [
          143.19395446777344,
          86.50433349609375
        ],
        [
          70.42578125,
          86.50433349609375
        ]
      ],
      "bbox": [
        70.42578125,
        72.46435546875,
        143.19395446777344,
        86.50433349609375
      ],
      "section_hierarchy": {
        "2": "/page/6/SectionHeader/1"
      },
      "images": {}
    },
    {
      "id": "/page/6/SectionHeader/2",
      "block_type": "SectionHeader",
      "html": "<h3><i>6.1. Recevabilité</i></h3>",
      "page": 232,
      "polygon": [
        [
          70.134765625,
          103.40008544921875
        ],
        [
          164.21998596191406,
          103.40008544921875
        ],
        [
          164.21998596191406,
          115.40008544921875
        ],
        [
          70.134765625,
          115.40008544921875
        ]
      ],
      "bbox": [
        70.134765625,
        103.40008544921875,
        164.21998596191406,
        115.40008544921875
      ],
      "section_hierarchy": {
        "2": "/page/6/SectionHeader/1",
        "3": "/page/6/SectionHeader/2"
      },
      "images": {}
    },
    {
      "id": "/page/6/SectionHeader/3",
      "block_type": "SectionHeader",
      "html": "<h3>6.1.1. Champ d'application</h3>",
      "page": 232,
      "polygon": [
        [
          70.8239974975586,
          132.2000732421875
        ],
        [
          212.89199829101562,
          132.2000732421875
        ],
        [
          212.89199829101562,
          144.2000732421875
        ],
        [
          70.8239974975586,
          144.2000732421875
        ]
      ],
      "bbox": [
        70.8239974975586,
        132.2000732421875,
        212.89199829101562,
        144.2000732421875
      ],
      "section_hierarchy": {
        "2": "/page/6/SectionHeader/1",
        "3": "/page/6/SectionHeader/3"
      },
      "images": {}
    },
    {
      "id": "/page/6/Text/4",
      "block_type": "Text",
      "html": "<p block-type=\"Text\">30. Dans le cadre de l'analyse de la recevabilité, il suffit d'établir que les faits dénoncés, s'ils étaient établis, seraient susceptibles de constituer une infraction au droit de la  concurrence belge ou européen. Dans le cas d'espèce, n2i a introduit une plainte assortie d'une demande de mesures provisoires le 6 juillet 2012 auprès de l'Auditorat du Conseil  de la concurrence conformément aux articles IV.41, §1, 2° du CDE et IV.64 du CDE (ex  articles 44, §1, 2° et 62 de la LPCE), dirigée contre la SCRTP et les Fédérations d'ETA ( l'EWETA, la FEBRAP et la VLAB)<i>.</i> Cette plainte dénonçait une entente, appelée  « Convention de Collaboration », signée en date du 3 mai 2011 entre les quatre  entreprises ou associations d'entreprises précitées et qui, d'après n2i, serait contraire à  l'article 2 de la LPCE (devenu entretemps l'article du IV.1 CDE).</p>",
      "page": 232,
      "polygon": [
        [
          76.828125,
          162.3974609375
        ],
        [
          527.5,
          162.3974609375
        ],
        [
          527.5,
          298.75146484375
        ],
        [
          76.828125,
          298.75146484375
        ]
      ],
      "bbox": [
        76.828125,
        162.3974609375,
        527.5,
        298.75146484375
      ],
      "section_hierarchy": {
        "2": "/page/6/SectionHeader/1",
        "3": "/page/6/SectionHeader/3"
      },
      "images": {}
    },
    {
      "id": "/page/6/SectionHeader/5",
      "block_type": "SectionHeader",
      "html": "<h3>6.1.2. Intérêt direct et actuel</h3>",
      "page": 232,
      "polygon": [
        [
          69.84375,
          312.7100830078125
        ],
        [
          220.0078125,
          312.7100830078125
        ],
        [
          220.0078125,
          324.7100830078125
        ],
        [
          69.84375,
          324.7100830078125
        ]
      ],
      "bbox": [
        69.84375,
        312.7100830078125,
        220.0078125,
        324.7100830078125
      ],
      "section_hierarchy": {
        "2": "/page/6/SectionHeader/1",
        "3": "/page/6/SectionHeader/5"
      },
      "images": {}
    },
    {
      "id": "/page/6/ListGroup/232",
      "block_type": "ListGroup",
      "html": "<p block-type=\"ListGroup\"><ul><li block-type=\"ListItem\">31. L'article 44, §1, 2° de la LPCE ainsi que l'article IV.41, §2 du CDE prévoient  l'instruction des affaires par l'Auditorat notamment sur plainte d'une personne physique  ou morale démontrant d'un intérêt direct et actuel en cas d'infraction à l'article IV.1,1 er CDE (ancien article 2 § 1 LPCE) ou IV.2 CDE (ancien article 3 LPCE). A cet égard, il y  a lieu d'interpréter la notion d'intérêt direct et actuel au regard de l'article 18 du Code  judiciaire qui vise tout avantage matériel ou moral effectif et non théorique que le  demandeur peut retirer de la demande qu'il intente au moment où il la forme (cf.  décisions de l'Auditorat de l'Autorité belge de la concurrence n° 2013-P/K-35-AUD du  1 er octobre 2013, <i>ClearChannel/JC Decaux </i>et 2014-P/K-23-AUD du 2 décembre 2014  <i>Handling CO/Sony Pictures Releasing).</i> La notion d'intérêt né et actuel rejoint celle de  l'intérêt requis pour saisir la Commission de l'Union européenne (cf. décision n° 2013- P/K-35-AUD précitée).</li><li block-type=\"ListItem\">32. La Partie plaignante collabore avec la SCRTP depuis 2008 en faisant appel aux ateliers  de différentes prisons afin d'exécuter les contrats de sous-traitance pour le compte de ses  propres clients. Elle justifiait d'un intérêt direct et actuel lors du dépôt de sa plainte dans  la mesure où la convention visait entre autres à récupérer des clients finaux des  intermédiaires et la réduction du recours aux intermédiaires, au détriment d'entreprises  telles que la partie plaignante.</li></ul></p>",
      "page": 232,
      "polygon": [
        [
          75.6640625,
          339.595703125
        ],
        [
          527.488037109375,
          339.595703125
        ],
        [
          527.488037109375,
          603.1318359375
        ],
        [
          75.6640625,
          603.1318359375
        ]
      ],
      "bbox": [
        75.6640625,
        339.595703125,
        527.488037109375,
        603.1318359375
      ],
      "section_hierarchy": {
        "2": "/page/6/SectionHeader/1",
        "3": "/page/6/SectionHeader/5"
      },
      "images": {}
    },
    {
      "id": "/page/6/SectionHeader/8",
      "block_type": "SectionHeader",
      "html": "<h3>6.1.3. Notion d'entreprise</h3>",
      "page": 232,
      "polygon": [
        [
          70.716796875,
          615.2800903320312
        ],
        [
          204.83999633789062,
          615.2800903320312
        ],
        [
          204.83999633789062,
          627.2800903320312
        ],
        [
          70.716796875,
          627.2800903320312
        ]
      ],
      "bbox": [
        70.716796875,
        615.2800903320312,
        204.83999633789062,
        627.2800903320312
      ],
      "section_hierarchy": {
        "2": "/page/6/SectionHeader/1",
        "3": "/page/6/SectionHeader/8"
      },
      "images": {}
    },
    {
      "id": "/page/6/Text/9",
      "block_type": "Text",
      "html": "<p block-type=\"Text\">33. Selon l'article I, 1, 1° CDE, il faut entendre par entreprise <i>«</i> <i>toute personne physique ou </i> <i>personne morale poursuivant de manière durable un but économique, y compris ses </i> <i>associations</i> <i>»</i>. En droit de la concurrence, une entreprise se définit comme une entité  qui poursuit de manière durable un but économique au sens large, indépendamment de  son statut juridique ou de son mode de financement, et ce même si elle est constituée  sous forme d'ASBL, pour autant qu'elle prenne part à une activité économique (cf.  décision du Président du Conseil de la concurrence, n° 2013-V/M-07 du 5 mars 2013  précitée).</p>",
      "page": 232,
      "polygon": [
        [
          75.6640625,
          645.7214508056641
        ],
        [
          527.488037109375,
          645.7214508056641
        ],
        [
          527.488037109375,
          754.4287109375
        ],
        [
          75.6640625,
          754.4287109375
        ]
      ],
      "bbox": [
        75.6640625,
        645.7214508056641,
        527.488037109375,
        754.4287109375
      ],
      "section_hierarchy": {
        "2": "/page/6/SectionHeader/1",
        "3": "/page/6/SectionHeader/8"
      },
      "images": {}
    },
    {
      "id": "/page/6/PageFooter/10",
      "block_type": "PageFooter",
      "html": "",
      "page": 232,
      "polygon": [
        [
          518.298828125,
          794.7197265625
        ],
        [
          524.701171875,
          794.7197265625
        ],
        [
          524.701171875,
          805.5434112548828
        ],
        [
          518.298828125,
          805.5434112548828
        ]
      ],
      "bbox": [
        518.298828125,
        794.7197265625,
        524.701171875,
        805.5434112548828
      ],
      "section_hierarchy": {
        "2": "/page/6/SectionHeader/1",
        "3": "/page/6/SectionHeader/8"
      },
      "images": {}
    },
    {
      "id": "/page/7/SectionHeader/0",
      "block_type": "SectionHeader",
      "html": "",
      "page": 160,
      "polygon": [
        [
          246.49023437499997,
          48.1025390625
        ],
        [
          347.6776123046875,
          48.1025390625
        ],
        [
          347.6776123046875,
          58.783447265625
        ],
        [
          246.49023437499997,
          58.783447265625
        ]
      ],
      "bbox": [
        246.49023437499997,
        48.1025390625,
        347.6776123046875,
        58.783447265625
      ],
      "section_hierarchy": {
        "2": "/page/6/SectionHeader/1",
        "3": "/page/6/SectionHeader/8",
        "4": "/page/7/SectionHeader/0"
      },
      "images": {}
    },
    {
      "id": "/page/7/Text/1",
      "block_type": "Text",
      "html": "<p block-type=\"Text\">34. La SCRTP doit être considérée comme une entreprise au sens du CDE, au vu de la  nature des services qu'elle fournit. Pour la même raison, il y a lieu de considérer les  ETA comme des entreprises et, partant, les Fédérations d'ETA comme des associations  d'entreprises au sens du CDE.</p>",
      "page": 160,
      "polygon": [
        [
          76.828125,
          71.9482421875
        ],
        [
          527.5239868164062,
          71.9482421875
        ],
        [
          527.5239868164062,
          125.44146728515625
        ],
        [
          76.828125,
          125.44146728515625
        ]
      ],
      "bbox": [
        76.828125,
        71.9482421875,
        527.5239868164062,
        125.44146728515625
      ],
      "section_hierarchy": {
        "2": "/page/6/SectionHeader/1",
        "3": "/page/6/SectionHeader/8",
        "4": "/page/7/SectionHeader/0"
      },
      "images": {}
    },
    {
      "id": "/page/7/SectionHeader/2",
      "block_type": "SectionHeader",
      "html": "<h3>6.1.4. Conclusion</h3>",
      "page": 160,
      "polygon": [
        [
          69.84375,
          139.3740234375
        ],
        [
          163.60800170898438,
          139.3740234375
        ],
        [
          163.60800170898438,
          151.40008544921875
        ],
        [
          69.84375,
          151.40008544921875
        ]
      ],
      "bbox": [
        69.84375,
        139.3740234375,
        163.60800170898438,
        151.40008544921875
      ],
      "section_hierarchy": {
        "2": "/page/6/SectionHeader/1",
        "3": "/page/7/SectionHeader/2"
      },
      "images": {}
    },
    {
      "id": "/page/7/Text/3",
      "block_type": "Text",
      "html": "<p block-type=\"Text\">35. Compte tenu de ce qui précède, la plainte introduite par n2i est recevable.</p>",
      "page": 160,
      "polygon": [
        [
          77.90399932861328,
          169.7978515625
        ],
        [
          448.9900207519531,
          169.7978515625
        ],
        [
          448.9900207519531,
          181.84149169921875
        ],
        [
          77.90399932861328,
          181.84149169921875
        ]
      ],
      "bbox": [
        77.90399932861328,
        169.7978515625,
        448.9900207519531,
        181.84149169921875
      ],
      "section_hierarchy": {
        "2": "/page/6/SectionHeader/1",
        "3": "/page/7/SectionHeader/2"
      },
      "images": {}
    },
    {
      "id": "/page/7/SectionHeader/4",
      "block_type": "SectionHeader",
      "html": "<h2><i>6.2. Analyse de la convention litigieuse</i> <i>au regard de l'article IV.</i><i>1 CDE</i> <i>et 101 TFUE</i></h2>",
      "page": 160,
      "polygon": [
        [
          70.8239974975586,
          209.60009765625
        ],
        [
          516.0159912109375,
          209.60009765625
        ],
        [
          516.0159912109375,
          235.40008544921875
        ],
        [
          70.8239974975586,
          235.40008544921875
        ]
      ],
      "bbox": [
        70.8239974975586,
        209.60009765625,
        516.0159912109375,
        235.40008544921875
      ],
      "section_hierarchy": {
        "2": "/page/7/SectionHeader/4"
      },
      "images": {}
    },
    {
      "id": "/page/7/Text/5",
      "block_type": "Text",
      "html": "<p block-type=\"Text\">36. Ce point ne fera pas l'objet de développement compte tenu de ce qui suit.</p>",
      "page": 160,
      "polygon": [
        [
          76.828125,
          251.59149169921875
        ],
        [
          448.3559875488281,
          251.59149169921875
        ],
        [
          448.3559875488281,
          263.947265625
        ],
        [
          76.828125,
          263.947265625
        ]
      ],
      "bbox": [
        76.828125,
        251.59149169921875,
        448.3559875488281,
        263.947265625
      ],
      "section_hierarchy": {
        "2": "/page/7/SectionHeader/4"
      },
      "images": {}
    },
    {
      "id": "/page/7/SectionHeader/6",
      "block_type": "SectionHeader",
      "html": "<h1><b>7. Classement</b> <b>eu égard à la politique des priorités et les moyens </b> <b>disponibles</b> <b>de l'Auditorat</b></h1>",
      "page": 160,
      "polygon": [
        [
          68.6796875,
          320.2724609375
        ],
        [
          508.5444641113281,
          320.2724609375
        ],
        [
          508.5444641113281,
          351.97430419921875
        ],
        [
          68.6796875,
          351.97430419921875
        ]
      ],
      "bbox": [
        68.6796875,
        320.2724609375,
        508.5444641113281,
        351.97430419921875
      ],
      "section_hierarchy": {
        "1": "/page/7/SectionHeader/6"
      },
      "images": {}
    },
    {
      "id": "/page/7/ListGroup/160",
      "block_type": "ListGroup",
      "html": "<p block-type=\"ListGroup\"><ul><li block-type=\"ListItem\">37. Les considérations suivantes justifient que l'instruction au fond ne soit pas poursuivie et  le dossier classé eu égard à la politique des priorités et les moyens disponibles de  l'Auditorat. Il ne peut cependant en être déduit que des accords de ce type pourraient être reconduits à l'avenir sans que l'Autorité belge de la Concurrence n'estime  nécessaire d'analyser leur violation potentielle avec le droit de la concurrence belge et  européen.</li><li block-type=\"ListItem\">38. Premièrement, les Fédérations d'ETA ont mis fin unilatéralement à la convention du 3  mai 2011 par lettres recommandées adressées à la SCRTP le 14 janvier 2013 par la  VLAB, le 7 février 2013 par la FEBRAP et le 8 février 2013 par l'EWETA.</li><li block-type=\"ListItem\">39. Deuxièmement, dans un mail adressé à l'Autorité belge de la Concurrence en date du 27  février 2015, la SCRTP confirme qu'elle n'applique plus la convention du 3 mai 2011 et  s'engage à supprimer toute référence à celle-ci sur quelque support que ce soit.</li><li block-type=\"ListItem\">40. Troisièmement l'Auditorat relève que les services concernés par la convention litigieuse  ne relèvent pas des secteurs retenus par l'Autorité belge de la Concurrence dans le cadre  de sa politique de priorités.</li><li block-type=\"ListItem\">41. Quatrièmement, l'Auditorat observe que le chiffre d'affaires de la SCRTP concerné par  la pratique en cause est limité.</li><li block-type=\"ListItem\">42. En conséquence, l'Auditorat de l'Autorité belge de la Concurrence est arrivé à la  conclusion qu'il n'est plus opportun de poursuivre l'instruction.</li></ul></p>",
      "page": 160,
      "polygon": [
        [
          75.6640625,
          370.3914794921875
        ],
        [
          527.4520263671875,
          370.3914794921875
        ],
        [
          527.4520263671875,
          699.748046875
        ],
        [
          75.6640625,
          699.748046875
        ]
      ],
      "bbox": [
        75.6640625,
        370.3914794921875,
        527.4520263671875,
        699.748046875
      ],
      "section_hierarchy": {
        "1": "/page/7/SectionHeader/6"
      },
      "images": {}
    },
    {
      "id": "/page/7/PageFooter/13",
      "block_type": "PageFooter",
      "html": "",
      "page": 160,
      "polygon": [
        [
          518.298828125,
          794.7197265625
        ],
        [
          524.701171875,
          794.7197265625
        ],
        [
          524.701171875,
          805.5434112548828
        ],
        [
          518.298828125,
          805.5434112548828
        ]
      ],
      "bbox": [
        518.298828125,
        794.7197265625,
        524.701171875,
        805.5434112548828
      ],
      "section_hierarchy": {
        "1": "/page/7/SectionHeader/6"
      },
      "images": {}
    },
    {
      "id": "/page/8/SectionHeader/0",
      "block_type": "SectionHeader",
      "html": "",
      "page": 68,
      "polygon": [
        [
          246.49023437499997,
          48.1025390625
        ],
        [
          347.6776123046875,
          48.1025390625
        ],
        [
          347.6776123046875,
          58.783447265625
        ],
        [
          246.49023437499997,
          58.783447265625
        ]
      ],
      "bbox": [
        246.49023437499997,
        48.1025390625,
        347.6776123046875,
        58.783447265625
      ],
      "section_hierarchy": {
        "1": "/page/7/SectionHeader/6",
        "4": "/page/8/SectionHeader/0"
      },
      "images": {}
    },
    {
      "id": "/page/8/SectionHeader/1",
      "block_type": "SectionHeader",
      "html": "<h2><b>Par ces motifs,</b></h2>",
      "page": 68,
      "polygon": [
        [
          69.84375,
          72.5595703125
        ],
        [
          158.37742614746094,
          72.5595703125
        ],
        [
          158.37742614746094,
          86.59954833984375
        ],
        [
          69.84375,
          86.59954833984375
        ]
      ],
      "bbox": [
        69.84375,
        72.5595703125,
        158.37742614746094,
        86.59954833984375
      ],
      "section_hierarchy": {
        "1": "/page/7/SectionHeader/6",
        "2": "/page/8/SectionHeader/1"
      },
      "images": {}
    },
    {
      "id": "/page/8/Text/2",
      "block_type": "Text",
      "html": "<p block-type=\"Text\">L'Auditorat de l'Autorité belge de la Concurrence,</p>",
      "page": 68,
      "polygon": [
        [
          69.26171875,
          115.84149169921875
        ],
        [
          313.10595703125,
          115.84149169921875
        ],
        [
          313.10595703125,
          127.84149169921875
        ],
        [
          69.26171875,
          127.84149169921875
        ]
      ],
      "bbox": [
        69.26171875,
        115.84149169921875,
        313.10595703125,
        127.84149169921875
      ],
      "section_hierarchy": {
        "1": "/page/7/SectionHeader/6",
        "2": "/page/8/SectionHeader/1"
      },
      "images": {}
    },
    {
      "id": "/page/8/Text/3",
      "block_type": "Text",
      "html": "<p block-type=\"Text\">Conformément à l'article IV.42, §2 du CDE,</p>",
      "page": 68,
      "polygon": [
        [
          69.26171875,
          143.44146728515625
        ],
        [
          288.77001953125,
          143.44146728515625
        ],
        [
          288.77001953125,
          155.44146728515625
        ],
        [
          69.26171875,
          155.44146728515625
        ]
      ],
      "bbox": [
        69.26171875,
        143.44146728515625,
        288.77001953125,
        155.44146728515625
      ],
      "section_hierarchy": {
        "1": "/page/7/SectionHeader/6",
        "2": "/page/8/SectionHeader/1"
      },
      "images": {}
    },
    {
      "id": "/page/8/ListGroup/68",
      "block_type": "ListGroup",
      "html": "<p block-type=\"ListGroup\"><ul><li block-type=\"ListItem\"> Déclare la plainte enregistré sous la référence CONC-P/K-12/0015 recevable</li><li block-type=\"ListItem\"> Classe la plainte eu égard à la politique des priorités et les moyens disponibles.</li></ul></p>",
      "page": 68,
      "polygon": [
        [
          105.9296875,
          170.6201171875
        ],
        [
          506.3799743652344,
          170.6201171875
        ],
        [
          506.3799743652344,
          196.84149169921875
        ],
        [
          105.9296875,
          196.84149169921875
        ]
      ],
      "bbox": [
        105.9296875,
        170.6201171875,
        506.3799743652344,
        196.84149169921875
      ],
      "section_hierarchy": {
        "1": "/page/7/SectionHeader/6",
        "2": "/page/8/SectionHeader/1"
      },
      "images": {}
    },
    {
      "id": "/page/8/Text/6",
      "block_type": "Text",
      "html": "<p block-type=\"Text\">Fait à BRUXELLES, le 18 mars 2015,</p>",
      "page": 68,
      "polygon": [
        [
          69.26171875,
          226.1214599609375
        ],
        [
          256.1300048828125,
          226.1214599609375
        ],
        [
          256.1300048828125,
          238.1214599609375
        ],
        [
          69.26171875,
          238.1214599609375
        ]
      ],
      "bbox": [
        69.26171875,
        226.1214599609375,
        256.1300048828125,
        238.1214599609375
      ],
      "section_hierarchy": {
        "1": "/page/7/SectionHeader/6",
        "2": "/page/8/SectionHeader/1"
      },
      "images": {}
    },
    {
      "id": "/page/8/Text/7",
      "block_type": "Text",
      "html": "<p block-type=\"Text\">Pour l'Auditorat,</p>",
      "page": 68,
      "polygon": [
        [
          69.84375,
          267.55145263671875
        ],
        [
          152.7480010986328,
          267.55145263671875
        ],
        [
          152.7480010986328,
          279.55145263671875
        ],
        [
          69.84375,
          279.55145263671875
        ]
      ],
      "bbox": [
        69.84375,
        267.55145263671875,
        152.7480010986328,
        279.55145263671875
      ],
      "section_hierarchy": {
        "1": "/page/7/SectionHeader/6",
        "2": "/page/8/SectionHeader/1"
      },
      "images": {}
    },
    {
      "id": "/page/8/Text/8",
      "block_type": "Text",
      "html": "<p block-type=\"Text\">Auditeur général Auditeur Auditeur</p>",
      "page": 68,
      "polygon": [
        [
          70.716796875,
          365.4970703125
        ],
        [
          477.19000244140625,
          365.4970703125
        ],
        [
          477.19000244140625,
          390.9873046875
        ],
        [
          70.716796875,
          390.9873046875
        ]
      ],
      "bbox": [
        70.716796875,
        365.4970703125,
        477.19000244140625,
        390.9873046875
      ],
      "section_hierarchy": {
        "1": "/page/7/SectionHeader/6",
        "2": "/page/8/SectionHeader/1"
      },
      "images": {}
    },
    {
      "id": "/page/8/Text/9",
      "block_type": "Text",
      "html": "<p block-type=\"Text\">Véronique Thirion Patrick Marchand Bert Stulens</p>",
      "page": 68,
      "polygon": [
        [
          70.8239974975586,
          364.1514587402344
        ],
        [
          488.469970703125,
          364.1514587402344
        ],
        [
          488.469970703125,
          388.931640625
        ],
        [
          70.8239974975586,
          388.931640625
        ]
      ],
      "bbox": [
        70.8239974975586,
        364.1514587402344,
        488.469970703125,
        388.931640625
      ],
      "section_hierarchy": {
        "1": "/page/7/SectionHeader/6",
        "2": "/page/8/SectionHeader/1"
      },
      "images": {}
    },
    {
      "id": "/page/8/Text/10",
      "block_type": "Text",
      "html": "<p block-type=\"Text\"></p>",
      "page": 68,
      "polygon": [
        [
          425.755859375,
          363.8525390625
        ],
        [
          482.21289062499994,
          363.8525390625
        ],
        [
          482.21289062499994,
          389.3427734375
        ],
        [
          425.755859375,
          389.3427734375
        ]
      ],
      "bbox": [
        425.755859375,
        363.8525390625,
        482.21289062499994,
        389.3427734375
      ],
      "section_hierarchy": {
        "1": "/page/7/SectionHeader/6",
        "2": "/page/8/SectionHeader/1"
      },
      "images": {}
    },
    {
      "id": "/page/8/PageFooter/11",
      "block_type": "PageFooter",
      "html": "",
      "page": 68,
      "polygon": [
        [
          518.0078125,
          794.7197265625
        ],
        [
          524.9921875,
          794.7197265625
        ],
        [
          524.9921875,
          805.5434112548828
        ],
        [
          518.0078125,
          805.5434112548828
        ]
      ],
      "bbox": [
        518.0078125,
        794.7197265625,
        524.9921875,
        805.5434112548828
      ],
      "section_hierarchy": {
        "1": "/page/7/SectionHeader/6",
        "2": "/page/8/SectionHeader/1"
      },
      "images": {}
    }
  ],
  "page_info": {
    "0": {
      "bbox": [
        0.0,
        0.0,
        596.0,
        842.0
      ],
      "polygon": [
        [
          0.0,
          0.0
        ],
        [
          596.0,
          0.0
        ],
        [
          596.0,
          842.0
        ],
        [
          0.0,
          842.0
        ]
      ]
    },
    "1": {
      "bbox": [
        0.0,
        0.0,
        596.0,
        842.0
      ],
      "polygon": [
        [
          0.0,
          0.0
        ],
        [
          596.0,
          0.0
        ],
        [
          596.0,
          842.0
        ],
        [
          0.0,
          842.0
        ]
      ]
    },
    "2": {
      "bbox": [
        0.0,
        0.0,
        596.0,
        842.0
      ],
      "polygon": [
        [
          0.0,
          0.0
        ],
        [
          596.0,
          0.0
        ],
        [
          596.0,
          842.0
        ],
        [
          0.0,
          842.0
        ]
      ]
    },
    "3": {
      "bbox": [
        0.0,
        0.0,
        596.0,
        842.0
      ],
      "polygon": [
        [
          0.0,
          0.0
        ],
        [
          596.0,
          0.0
        ],
        [
          596.0,
          842.0
        ],
        [
          0.0,
          842.0
        ]
      ]
    },
    "4": {
      "bbox": [
        0.0,
        0.0,
        596.0,
        842.0
      ],
      "polygon": [
        [
          0.0,
          0.0
        ],
        [
          596.0,
          0.0
        ],
        [
          596.0,
          842.0
        ],
        [
          0.0,
          842.0
        ]
      ]
    },
    "5": {
      "bbox": [
        0.0,
        0.0,
        596.0,
        842.0
      ],
      "polygon": [
        [
          0.0,
          0.0
        ],
        [
          596.0,
          0.0
        ],
        [
          596.0,
          842.0
        ],
        [
          0.0,
          842.0
        ]
      ]
    },
    "6": {
      "bbox": [
        0.0,
        0.0,
        596.0,
        842.0
      ],
      "polygon": [
        [
          0.0,
          0.0
        ],
        [
          596.0,
          0.0
        ],
        [
          596.0,
          842.0
        ],
        [
          0.0,
          842.0
        ]
      ]
    },
    "7": {
      "bbox": [
        0.0,
        0.0,
        596.0,
        842.0
      ],
      "polygon": [
        [
          0.0,
          0.0
        ],
        [
          596.0,
          0.0
        ],
        [
          596.0,
          842.0
        ],
        [
          0.0,
          842.0
        ]
      ]
    },
    "8": {
      "bbox": [
        0.0,
        0.0,
        596.0,
        842.0
      ],
      "polygon": [
        [
          0.0,
          0.0
        ],
        [
          596.0,
          0.0
        ],
        [
          596.0,
          842.0
        ],
        [
          0.0,
          842.0
        ]
      ]
    }
  }
}